[{"id":"nb8b","title":"Vintage Queen Quality 5 Lb. Salted Nuts Advertising Tin Can!--peanuts--lancaster","link":"http://rover.ebay.com/rover/1/711-53200-19255-0/1?campid=5336393622&toolid=10013&customId=advertising/tins&mpre=http://www.ebay.com/itm/121851035434","meta":{"price":9300,"date":{"formatted":"2016-01-10T08:00:00.000Z","origin":"-11 hours ago"},"bids":10,"watchers":15},"src":{"original":"http://thumbs3.ebaystatic.com/m/mn128oq-rjE-vnDqJES69XQ/140.jpg","local":"2016/01/10/nb8b/t.jpg"},"images":{"original":["http://i.ebayimg.com/images/g/U1YAAOSwSHZWgYPA/s-l64.jpg","http://i.ebayimg.com/images/g/wYcAAOSwhkRWgYPI/s-l64.jpg","http://i.ebayimg.com/images/g/1osAAOSwSdZWgYPP/s-l64.jpg","http://i.ebayimg.com/images/g/LAQAAOSwUdlWgYPW/s-l64.jpg","http://i.ebayimg.com/images/g/x6kAAOSwYaFWgYPe/s-l64.jpg","http://i.ebayimg.com/images/g/yEkAAOSwYaFWgYPk/s-l64.jpg","http://i.ebayimg.com/images/g/LoUAAOSwk1JWgYPr/s-l64.jpg"],"local":["2016/01/10/nb8b/i_0.jpg","2016/01/10/nb8b/i_1.jpg","2016/01/10/nb8b/i_2.jpg","2016/01/10/nb8b/i_3.jpg","2016/01/10/nb8b/i_4.jpg","2016/01/10/nb8b/i_5.jpg","2016/01/10/nb8b/i_6.jpg"]}},{"id":"lgg6","title":"Antique Kelly Douglas Vancouver Hilla Coffee Tin Pain Canadian ","link":"http://rover.ebay.com/rover/1/711-53200-19255-0/1?campid=5336393622&toolid=10013&customId=advertising/tins&mpre=http://www.ebay.com/itm/381509085980","meta":{"price":4800,"date":{"formatted":"2016-01-10T08:00:00.000Z","origin":"-2 hours ago"},"bids":21,"watchers":29},"src":{"original":"http://thumbs1.ebaystatic.com/m/mj1CoRWNy51qq3xIxEFZh_w/140.jpg","local":"2016/01/10/lgg6/t.jpg"},"images":{"original":["http://i.ebayimg.com/images/g/z~EAAOSwL7VWiSnD/s-l64.jpg","http://i.ebayimg.com/images/g/veoAAOSwHaBWiSnH/s-l64.jpg","http://i.ebayimg.com/images/g/hEEAAOSwZG9WiSnM/s-l64.jpg","http://i.ebayimg.com/images/g/EhYAAOSwT~9WiSnQ/s-l64.jpg","http://i.ebayimg.com/images/g/v5cAAOSwHaBWiSnV/s-l64.jpg","http://i.ebayimg.com/images/g/iLkAAOSwYIhWiSnZ/s-l64.jpg"],"local":["2016/01/10/lgg6/i_0.jpg","2016/01/10/lgg6/i_1.jpg","2016/01/10/lgg6/i_2.jpg","2016/01/10/lgg6/i_3.jpg","2016/01/10/lgg6/i_4.jpg","2016/01/10/lgg6/i_5.jpg"]}},{"id":"gnsv","title":"Rare Antique Wood's Mince Meat 3 Lb Advertising Tin Can--baltimore, Maryland--md","link":"http://rover.ebay.com/rover/1/711-53200-19255-0/1?campid=5336393622&toolid=10013&customId=advertising/tins&mpre=http://www.ebay.com/itm/351615070310","meta":{"price":3300,"date":{"formatted":"2016-01-10T08:00:00.000Z","origin":"-11 hours ago"},"bids":5,"watchers":11},"src":{"original":"http://thumbs3.ebaystatic.com/m/mzLxHjO15ep2XZmoJeYQm8A/140.jpg","local":"2016/01/10/gnsv/t.jpg"},"images":{"original":["http://i.ebayimg.com/images/g/vv4AAOSw~otWgZZo/s-l64.jpg","http://i.ebayimg.com/images/g/ltMAAOSwhkRWgZZ1/s-l64.jpg","http://i.ebayimg.com/images/g/l9UAAOSwhkRWgZaD/s-l64.jpg","http://i.ebayimg.com/images/g/wDIAAOSw3KFWgZaL/s-l64.jpg","http://i.ebayimg.com/images/g/wVIAAOSw3KFWgZaV/s-l64.jpg","http://i.ebayimg.com/images/g/6jUAAOSwNyFWgZac/s-l64.jpg","http://i.ebayimg.com/images/g/DOMAAOSwSHZWgZal/s-l64.jpg","http://i.ebayimg.com/images/g/nAQAAOSwhkRWgZau/s-l64.jpg","http://i.ebayimg.com/images/g/YrsAAOSwCQNWgZa4/s-l64.jpg"],"local":["2016/01/10/gnsv/i_0.jpg","2016/01/10/gnsv/i_1.jpg","2016/01/10/gnsv/i_2.jpg","2016/01/10/gnsv/i_3.jpg","2016/01/10/gnsv/i_4.jpg","2016/01/10/gnsv/i_5.jpg","2016/01/10/gnsv/i_6.jpg","2016/01/10/gnsv/i_7.jpg","2016/01/10/gnsv/i_8.jpg"]}},{"id":"w2tz","title":"Vintage Antique Tin, Colgan's Mint Chips Gum, Excellent Condition ","link":"http://rover.ebay.com/rover/1/711-53200-19255-0/1?campid=5336393622&toolid=10013&customId=advertising/tins&mpre=http://www.ebay.com/itm/291652062557","meta":{"price":1999,"date":{"formatted":"2016-01-10T08:00:00.000Z","origin":"-18 mins ago"},"bids":3,"watchers":4},"src":{"original":"http://thumbs2.ebaystatic.com/m/mJz8B9pumOxpJ1FUhHgeQyQ/140.jpg","local":"2016/01/10/w2tz/t.jpg"},"images":{"original":["http://i.ebayimg.com/images/g/YaIAAOSwa-dWiTLT/s-l64.jpg","http://i.ebayimg.com/images/g/XWQAAOSwGotWiTLj/s-l64.jpg","http://i.ebayimg.com/images/g/rU0AAOSwL7VWiTMI/s-l64.jpg"],"local":["2016/01/10/w2tz/i_0.jpg","2016/01/10/w2tz/i_1.jpg","2016/01/10/w2tz/i_2.jpg"]}},{"id":"v0cs","title":"Vintage Marlboro 100 Cigarette Philip Morris & Co. Painted Tobacco Tin ","link":"http://rover.ebay.com/rover/1/711-53200-19255-0/1?campid=5336393622&toolid=10013&customId=advertising/tins&mpre=http://www.ebay.com/itm/361462354375","meta":{"price":1800,"date":{"formatted":"2016-01-10T08:00:00.000Z","origin":"-29 mins ago"},"bids":7,"watchers":6},"src":{"original":"http://thumbs4.ebaystatic.com/m/mNACFh57OiuLQ1hXnO2RX8A/140.jpg","local":"2016/01/10/v0cs/t.jpg"},"images":{"original":["http://i.ebayimg.com/images/g/cyAAAOSwp5JWW5n0/s-l64.jpg","http://i.ebayimg.com/images/g/6OAAAOSwgyxWW5n5/s-l64.jpg","http://i.ebayimg.com/images/g/xG4AAOSwnH1WW5n~/s-l64.jpg"],"local":["2016/01/10/v0cs/i_0.jpg","2016/01/10/v0cs/i_1.jpg","2016/01/10/v0cs/i_2.jpg"]}},{"id":"o40g","title":"Antique Vintage 18k Brand Coffee Tin Bank!--can--tea","link":"http://rover.ebay.com/rover/1/711-53200-19255-0/1?campid=5336393622&toolid=10013&customId=advertising/tins&mpre=http://www.ebay.com/itm/351617779315","meta":{"price":1550,"date":{"formatted":"2016-01-10T08:00:00.000Z","origin":"-11 hours ago"},"bids":3,"watchers":8},"src":{"original":"http://thumbs4.ebaystatic.com/m/mKPFNu0uLV-vz2j_M0-CiYg/140.jpg","local":"2016/01/10/o40g/t.jpg"},"images":{"original":["http://i.ebayimg.com/images/g/BqQAAOSwGotWhWZk/s-l64.jpg","http://i.ebayimg.com/images/g/BzsAAOSwGotWhWZs/s-l64.jpg","http://i.ebayimg.com/images/g/g-MAAOSwX~dWhWZ2/s-l64.jpg","http://i.ebayimg.com/images/g/CKkAAOSwGotWhWZ~/s-l64.jpg","http://i.ebayimg.com/images/g/7~4AAOSwFqJWhWaH/s-l64.jpg","http://i.ebayimg.com/images/g/180AAOSwKtlWhWaR/s-l64.jpg","http://i.ebayimg.com/images/g/tlsAAOSwYIhWhWaa/s-l64.jpg","http://i.ebayimg.com/images/g/Dy4AAOSwJkJWhWak/s-l64.jpg","http://i.ebayimg.com/images/g/8ucAAOSwFqJWhWas/s-l64.jpg"],"local":["2016/01/10/o40g/i_0.jpg","2016/01/10/o40g/i_1.jpg","2016/01/10/o40g/i_2.jpg","2016/01/10/o40g/i_3.jpg","2016/01/10/o40g/i_4.jpg","2016/01/10/o40g/i_5.jpg","2016/01/10/o40g/i_6.jpg","2016/01/10/o40g/i_7.jpg","2016/01/10/o40g/i_8.jpg"]}},{"id":"3htv","title":"Vintage Jacob & Co. Cracker Tin- Extra Light Cream Crackers Box-england-","link":"http://rover.ebay.com/rover/1/711-53200-19255-0/1?campid=5336393622&toolid=10013&customId=advertising/tins&mpre=http://www.ebay.com/itm/321965709186","meta":{"price":1550,"date":{"formatted":"2016-01-10T08:00:00.000Z","origin":"-4 mins ago"},"bids":3,"watchers":2},"src":{"original":"http://thumbs3.ebaystatic.com/m/mGUJWFnnHrQpB2sMb25__Sw/140.jpg","local":"2016/01/10/3htv/t.jpg"},"images":{"original":["http://i.ebayimg.com/images/g/MoIAAOSwKtlWiThP/s-l64.jpg","http://i.ebayimg.com/images/g/BmsAAOSwYIhWiThP/s-l64.jpg","http://i.ebayimg.com/images/g/xKsAAOSwLN5WiThR/s-l64.jpg"],"local":["2016/01/10/3htv/i_0.jpg","2016/01/10/3htv/i_1.jpg","2016/01/10/3htv/i_2.jpg"]}},{"id":"yii8","title":"2 Vintage 4lb Lard Pails - Southern Star - Louisville, Ky & Armour - Phoeniz, Az","link":"http://rover.ebay.com/rover/1/711-53200-19255-0/1?campid=5336393622&toolid=10013&customId=advertising/tins&mpre=http://www.ebay.com/itm/252236399454","meta":{"price":1500,"date":{"formatted":"2016-01-10T08:00:00.000Z","origin":"-2 hours ago"},"bids":1,"watchers":0},"src":{"original":"http://thumbs3.ebaystatic.com/m/m4WOcn9Yp38FX1Gh1bv1dPQ/140.jpg","local":"2016/01/10/yii8/t.jpg"},"images":{"original":["http://i.ebayimg.com/images/g/naYAAOSwKtlWiSDX/s-l64.jpg","http://i.ebayimg.com/images/g/xfwAAOSwwPhWiSDd/s-l64.jpg","http://i.ebayimg.com/images/g/5NIAAOSwaA5WiSDi/s-l64.jpg","http://i.ebayimg.com/images/g/iIAAAOSwoydWiSDn/s-l64.jpg","http://i.ebayimg.com/images/g/KJ0AAOSwT~9WiSDr/s-l64.jpg","http://i.ebayimg.com/images/g/-rYAAOSwL7VWiSDx/s-l64.jpg","http://i.ebayimg.com/images/g/trgAAOSwGotWiSD2/s-l64.jpg","http://i.ebayimg.com/images/g/ZhkAAOSwLN5WiSD7/s-l64.jpg","http://i.ebayimg.com/images/g/55AAAOSwaA5WiSEB/s-l64.jpg","http://i.ebayimg.com/images/g/zJYAAOSwFqJWiSEG/s-l64.jpg"],"local":["2016/01/10/yii8/i_0.jpg","2016/01/10/yii8/i_1.jpg","2016/01/10/yii8/i_2.jpg","2016/01/10/yii8/i_3.jpg","2016/01/10/yii8/i_4.jpg","2016/01/10/yii8/i_5.jpg","2016/01/10/yii8/i_6.jpg","2016/01/10/yii8/i_7.jpg","2016/01/10/yii8/i_8.jpg","2016/01/10/yii8/i_9.jpg"]}},{"id":"rc8i","title":"1931 Folgers Coffee Tin","link":"http://rover.ebay.com/rover/1/711-53200-19255-0/1?campid=5336393622&toolid=10013&customId=advertising/tins&mpre=http://www.ebay.com/itm/141867713528","meta":{"price":1200,"date":{"formatted":"2016-01-10T08:00:00.000Z","origin":"-39 mins ago"},"bids":1,"watchers":0},"src":{"original":"http://thumbs1.ebaystatic.com/m/mhOZTl8BQvVg7865naNovlg/140.jpg","local":"2016/01/10/rc8i/t.jpg"},"images":{"original":["http://i.ebayimg.com/images/g/KUgAAOSwYaFWfvaT/s-l64.jpg","http://i.ebayimg.com/images/g/Mv8AAOSwo3pWfvae/s-l64.jpg","http://i.ebayimg.com/images/g/tdAAAOSwSHZWfvag/s-l64.jpg","http://i.ebayimg.com/images/g/ozYAAOSwCQNWfvaj/s-l64.jpg","http://i.ebayimg.com/images/g/ti8AAOSwSHZWfval/s-l64.jpg","http://i.ebayimg.com/images/g/r7sAAOSwNyFWfvao/s-l64.jpg","http://i.ebayimg.com/images/g/PDYAAOSwJcZWfvar/s-l64.jpg","http://i.ebayimg.com/images/g/xgIAAOSwSdZWfvat/s-l64.jpg"],"local":["2016/01/10/rc8i/i_0.jpg","2016/01/10/rc8i/i_1.jpg","2016/01/10/rc8i/i_2.jpg","2016/01/10/rc8i/i_3.jpg","2016/01/10/rc8i/i_4.jpg","2016/01/10/rc8i/i_5.jpg","2016/01/10/rc8i/i_6.jpg","2016/01/10/rc8i/i_7.jpg"]}},{"id":"k9cy","title":"Vintage Cigarette/tobacco Tin/panther Mignon Wear/used","link":"http://rover.ebay.com/rover/1/711-53200-19255-0/1?campid=5336393622&toolid=10013&customId=advertising/tins&mpre=http://www.ebay.com/itm/381509112104","meta":{"price":289,"date":{"formatted":"2016-01-10T08:00:00.000Z","origin":"-5 mins ago"},"bids":1,"watchers":0},"src":{"original":"http://thumbs1.ebaystatic.com/m/mgm7zn7I86jPyGTDNO3Gabw/140.jpg","local":"2016/01/10/k9cy/t.jpg"},"images":{"original":["http://i.ebayimg.com/images/g/4J4AAOSwFqJWiTas/s-l64.jpg","http://i.ebayimg.com/images/g/1ZsAAOSwa-dWiTcF/s-l64.jpg"],"local":["2016/01/10/k9cy/i_0.jpg","2016/01/10/k9cy/i_1.jpg"]}},{"id":"ey2c","title":" Vintage Union Leader Tobacco Tin","link":"http://rover.ebay.com/rover/1/711-53200-19255-0/1?campid=5336393622&toolid=10013&customId=advertising/tins&mpre=http://www.ebay.com/itm/181980110614","meta":{"price":199,"date":{"formatted":"2016-01-10T08:00:00.000Z","origin":"-2 mins ago"},"bids":1,"watchers":1},"src":{"original":"http://thumbs3.ebaystatic.com/m/mWrkmcP2OxsUnKWvPkQbkpg/140.jpg","local":"2016/01/10/ey2c/t.jpg"},"images":{"original":["http://i.ebayimg.com/images/g/MuUAAOSwa-dWiTop/s-l64.jpg","http://i.ebayimg.com/images/g/rjoAAOSwX~dWiTh9/s-l64.jpg","http://i.ebayimg.com/images/g/lcwAAOSwHaBWiTpA/s-l64.jpg","http://i.ebayimg.com/images/g/zaYAAOSwLN5WiTiU/s-l64.jpg"],"local":["2016/01/10/ey2c/i_0.jpg","2016/01/10/ey2c/i_1.jpg","2016/01/10/ey2c/i_2.jpg","2016/01/10/ey2c/i_3.jpg"]}}]