[{"id":"mzh9","title":"Mayo Cut Plug Tin ","link":"http://rover.ebay.com/rover/1/711-53200-19255-0/1?campid=5336393622&toolid=10013&customId=advertising/tins&mpre=http://www.ebay.com/itm/331751314197","meta":{"price":24999,"date":{"formatted":"2016-01-14T08:00:00.000Z","origin":"-20 hours ago"},"bids":1,"watchers":1},"src":{"original":"http://thumbs2.ebaystatic.com/m/mFF3oaSEmDr1SkkSgaS7URg/140.jpg","local":"2016/01/14/mzh9/t.jpg"},"images":{"original":["http://i.ebayimg.com/images/g/CMwAAOSwa-dWkAce/s-l64.jpg","http://i.ebayimg.com/images/g/W0QAAOSwFqJWi~2f/s-l64.jpg","http://i.ebayimg.com/images/g/rVUAAOSwoydWi~2u/s-l64.jpg","http://i.ebayimg.com/images/g/5GcAAOSwKtlWkAc7/s-l64.jpg","http://i.ebayimg.com/images/g/jCoAAOSwL7VWjAWJ/s-l64.jpg","http://i.ebayimg.com/images/g/MjcAAOSwT~9WkAb-/s-l64.jpg","http://i.ebayimg.com/images/g/K8sAAOSwFqJWkAlk/s-l64.jpg","http://i.ebayimg.com/images/g/eqcAAOSwT~9Wi~1I/s-l64.jpg","http://i.ebayimg.com/images/g/7s8AAOSwKtlWkAeO/s-l64.jpg","http://i.ebayimg.com/images/g/80QAAOSwKtlWkAet/s-l64.jpg","http://i.ebayimg.com/images/g/5T4AAOSwYIhWkAdv/s-l64.jpg"],"local":["2016/01/14/mzh9/i_0.jpg","2016/01/14/mzh9/i_1.jpg","2016/01/14/mzh9/i_2.jpg","2016/01/14/mzh9/i_3.jpg","2016/01/14/mzh9/i_4.jpg","2016/01/14/mzh9/i_5.jpg","2016/01/14/mzh9/i_6.jpg","2016/01/14/mzh9/i_7.jpg","2016/01/14/mzh9/i_8.jpg","2016/01/14/mzh9/i_9.jpg","2016/01/14/mzh9/i_10.jpg"]}},{"id":"mqtr","title":"Rare Mid 20th Century Zig Zag Blue Rolling Papers Tobacco Dispenser Tin Sign","link":"http://rover.ebay.com/rover/1/711-53200-19255-0/1?campid=5336393622&toolid=10013&customId=advertising/tins&mpre=http://www.ebay.com/itm/281902999580","meta":{"price":21138,"date":{"formatted":"2016-01-14T08:00:00.000Z","origin":"-12 hours ago"},"bids":17,"watchers":31},"src":{"original":"http://thumbs1.ebaystatic.com/m/m8odkTpgnsOBhCeXs1MjEKA/140.jpg","local":"2016/01/14/mqtr/t.jpg"},"images":{"original":["http://i.ebayimg.com/images/g/OEsAAOSwT~9Wjdtj/s-l64.jpg","http://i.ebayimg.com/images/g/Nf8AAOSwwPhWjdRD/s-l64.jpg","http://i.ebayimg.com/images/g/kToAAOSwHnFVtstT/s-l64.jpg","http://i.ebayimg.com/images/g/kjIAAOSwHnFVtstc/s-l64.jpg","http://i.ebayimg.com/images/g/k5kAAOSwHnFVtstp/s-l64.jpg","http://i.ebayimg.com/images/g/z5cAAOSwDNdVtstx/s-l64.jpg","http://i.ebayimg.com/images/g/KVgAAOSwgQ9Vtst3/s-l64.jpg","http://i.ebayimg.com/images/g/034AAOSw9N1VtsuH/s-l64.jpg"],"local":["2016/01/14/mqtr/i_0.jpg","2016/01/14/mqtr/i_1.jpg","2016/01/14/mqtr/i_2.jpg","2016/01/14/mqtr/i_3.jpg","2016/01/14/mqtr/i_4.jpg","2016/01/14/mqtr/i_5.jpg","2016/01/14/mqtr/i_6.jpg","2016/01/14/mqtr/i_7.jpg"]}},{"id":"98hv","title":"Rare Early 20th Century Zig Zag White Rolling Papers Tobacco Dispenser Tin Sign","link":"http://rover.ebay.com/rover/1/711-53200-19255-0/1?campid=5336393622&toolid=10013&customId=advertising/tins&mpre=http://www.ebay.com/itm/281902985889","meta":{"price":18750,"date":{"formatted":"2016-01-14T08:00:00.000Z","origin":"-12 hours ago"},"bids":40,"watchers":22},"src":{"original":"http://thumbs2.ebaystatic.com/m/mmn-tI3vAEfPXfs-QHsuHLA/140.jpg","local":"2016/01/14/98hv/t.jpg"},"images":{"original":["http://i.ebayimg.com/images/g/N-EAAOSwHaBWjdKl/s-l64.jpg","http://i.ebayimg.com/images/g/Nf8AAOSwwPhWjdRD/s-l64.jpg","http://i.ebayimg.com/images/g/kToAAOSwHnFVtstT/s-l64.jpg","http://i.ebayimg.com/images/g/kjIAAOSwHnFVtstc/s-l64.jpg","http://i.ebayimg.com/images/g/k5kAAOSwHnFVtstp/s-l64.jpg","http://i.ebayimg.com/images/g/z5cAAOSwDNdVtstx/s-l64.jpg","http://i.ebayimg.com/images/g/KVgAAOSwgQ9Vtst3/s-l64.jpg","http://i.ebayimg.com/images/g/034AAOSw9N1VtsuH/s-l64.jpg"],"local":["2016/01/14/98hv/i_0.jpg","2016/01/14/98hv/i_1.jpg","2016/01/14/98hv/i_2.jpg","2016/01/14/98hv/i_3.jpg","2016/01/14/98hv/i_4.jpg","2016/01/14/98hv/i_5.jpg","2016/01/14/98hv/i_6.jpg","2016/01/14/98hv/i_7.jpg"]}},{"id":"m8aa","title":"Rare Early 20th Century Zig Zag White Rolling Papers Tobacco Dispenser Tin Sign","link":"http://rover.ebay.com/rover/1/711-53200-19255-0/1?campid=5336393622&toolid=10013&customId=advertising/tins&mpre=http://www.ebay.com/itm/281902991182","meta":{"price":17350,"date":{"formatted":"2016-01-14T08:00:00.000Z","origin":"-12 hours ago"},"bids":33,"watchers":28},"src":{"original":"http://thumbs3.ebaystatic.com/m/m8gN9cblxVCPwuS3JFKTBqQ/140.jpg","local":"2016/01/14/m8aa/t.jpg"},"images":{"original":["http://i.ebayimg.com/images/g/5LEAAOSwX~dWjdcL/s-l64.jpg","http://i.ebayimg.com/images/g/Nf8AAOSwwPhWjdRD/s-l64.jpg","http://i.ebayimg.com/images/g/kToAAOSwHnFVtstT/s-l64.jpg","http://i.ebayimg.com/images/g/kjIAAOSwHnFVtstc/s-l64.jpg","http://i.ebayimg.com/images/g/k5kAAOSwHnFVtstp/s-l64.jpg","http://i.ebayimg.com/images/g/z5cAAOSwDNdVtstx/s-l64.jpg","http://i.ebayimg.com/images/g/KVgAAOSwgQ9Vtst3/s-l64.jpg","http://i.ebayimg.com/images/g/034AAOSw9N1VtsuH/s-l64.jpg"],"local":["2016/01/14/m8aa/i_0.jpg","2016/01/14/m8aa/i_1.jpg","2016/01/14/m8aa/i_2.jpg","2016/01/14/m8aa/i_3.jpg","2016/01/14/m8aa/i_4.jpg","2016/01/14/m8aa/i_5.jpg","2016/01/14/m8aa/i_6.jpg","2016/01/14/m8aa/i_7.jpg"]}},{"id":"49ei","title":"Wedding Breakfast Coffee Tin Ca. 1906","link":"http://rover.ebay.com/rover/1/711-53200-19255-0/1?campid=5336393622&toolid=10013&customId=advertising/tins&mpre=http://www.ebay.com/itm/201499593168","meta":{"price":15249,"date":{"formatted":"2016-01-14T08:00:00.000Z","origin":"-19 hours ago"},"bids":9,"watchers":9},"src":{"original":"http://thumbs1.ebaystatic.com/m/m2eOnlF7Sv8BuSSb62GLftQ/140.jpg","local":"2016/01/14/49ei/t.jpg"},"images":{"original":["http://i.ebayimg.com/images/g/47MAAOSwHaBWkBTv/s-l64.jpg","http://i.ebayimg.com/images/g/4GgAAOSw5dNWkBT0/s-l64.jpg","http://i.ebayimg.com/images/g/LOoAAOSwJkJWkBT4/s-l64.jpg","http://i.ebayimg.com/images/g/4KUAAOSwGotWkBT8/s-l64.jpg","http://i.ebayimg.com/images/g/Z44AAOSwYIhWkBT~/s-l64.jpg","http://i.ebayimg.com/images/g/4b0AAOSw5dNWkBUB/s-l64.jpg","http://i.ebayimg.com/images/g/fjoAAOSwLN5WkBUG/s-l64.jpg","http://i.ebayimg.com/images/g/5uAAAOSwHaBWkBUJ/s-l64.jpg"],"local":["2016/01/14/49ei/i_0.jpg","2016/01/14/49ei/i_1.jpg","2016/01/14/49ei/i_2.jpg","2016/01/14/49ei/i_3.jpg","2016/01/14/49ei/i_4.jpg","2016/01/14/49ei/i_5.jpg","2016/01/14/49ei/i_6.jpg","2016/01/14/49ei/i_7.jpg"]}},{"id":"64q4","title":"Rare Early 20th Century Zig Zag White Rolling Papers Tobacco Dispenser Tin Sign","link":"http://rover.ebay.com/rover/1/711-53200-19255-0/1?campid=5336393622&toolid=10013&customId=advertising/tins&mpre=http://www.ebay.com/itm/281902989525","meta":{"price":13352,"date":{"formatted":"2016-01-14T08:00:00.000Z","origin":"-12 hours ago"},"bids":22,"watchers":25},"src":{"original":"http://thumbs2.ebaystatic.com/m/mnfH_BZsaU-4yUEjhs4gUhA/140.jpg","local":"2016/01/14/64q4/t.jpg"},"images":{"original":["http://i.ebayimg.com/images/g/P4YAAOSwFqJWjdYK/s-l64.jpg","http://i.ebayimg.com/images/g/Nf8AAOSwwPhWjdRD/s-l64.jpg","http://i.ebayimg.com/images/g/kToAAOSwHnFVtstT/s-l64.jpg","http://i.ebayimg.com/images/g/kjIAAOSwHnFVtstc/s-l64.jpg","http://i.ebayimg.com/images/g/k5kAAOSwHnFVtstp/s-l64.jpg","http://i.ebayimg.com/images/g/z5cAAOSwDNdVtstx/s-l64.jpg","http://i.ebayimg.com/images/g/KVgAAOSwgQ9Vtst3/s-l64.jpg","http://i.ebayimg.com/images/g/034AAOSw9N1VtsuH/s-l64.jpg"],"local":["2016/01/14/64q4/i_0.jpg","2016/01/14/64q4/i_1.jpg","2016/01/14/64q4/i_2.jpg","2016/01/14/64q4/i_3.jpg","2016/01/14/64q4/i_4.jpg","2016/01/14/64q4/i_5.jpg","2016/01/14/64q4/i_6.jpg","2016/01/14/64q4/i_7.jpg"]}},{"id":"p34a","title":"Vintage Tone's Coffee Key Wind Tin Can's 2 Original Seldom Seen Rare 1930\"s","link":"http://rover.ebay.com/rover/1/711-53200-19255-0/1?campid=5336393622&toolid=10013&customId=advertising/tins&mpre=http://www.ebay.com/itm/281902941704","meta":{"price":12000,"date":{"formatted":"2016-01-14T08:00:00.000Z","origin":"-14 hours ago"},"bids":16,"watchers":10},"src":{"original":"http://thumbs1.ebaystatic.com/m/mX8YbgQ6GXUgSTWrrnJxiYw/140.jpg","local":"2016/01/14/p34a/t.jpg"},"images":{"original":["http://i.ebayimg.com/images/g/3UIAAOSwZG9WjZQ-/s-l64.jpg","http://i.ebayimg.com/images/g/A9cAAOSwKtlWjZRL/s-l64.jpg","http://i.ebayimg.com/images/g/Mp8AAOSwL7VWjZRS/s-l64.jpg","http://i.ebayimg.com/images/g/BZ0AAOSwKtlWjZRb/s-l64.jpg","http://i.ebayimg.com/images/g/GfoAAOSwa-dWjZRl/s-l64.jpg","http://i.ebayimg.com/images/g/NVUAAOSwL7VWjZRz/s-l64.jpg","http://i.ebayimg.com/images/g/eMgAAOSw5dNWjZR-/s-l64.jpg","http://i.ebayimg.com/images/g/Cf0AAOSwKtlWjZSL/s-l64.jpg","http://i.ebayimg.com/images/g/CXAAAOSwHaBWjZSU/s-l64.jpg","http://i.ebayimg.com/images/g/c6UAAOSwT~9WjZSe/s-l64.jpg","http://i.ebayimg.com/images/g/IS4AAOSwa-dWjZSz/s-l64.jpg","http://i.ebayimg.com/images/g/EiAAAOSwKtlWjZTf/s-l64.jpg"],"local":["2016/01/14/p34a/i_0.jpg","2016/01/14/p34a/i_1.jpg","2016/01/14/p34a/i_2.jpg","2016/01/14/p34a/i_3.jpg","2016/01/14/p34a/i_4.jpg","2016/01/14/p34a/i_5.jpg","2016/01/14/p34a/i_6.jpg","2016/01/14/p34a/i_7.jpg","2016/01/14/p34a/i_8.jpg","2016/01/14/p34a/i_9.jpg","2016/01/14/p34a/i_10.jpg","2016/01/14/p34a/i_11.jpg"]}},{"id":"9loc","title":"Vintage Red Bird Coffee Tin Imported & Roasted By The Midland Grocery Co Of Ohio","link":"http://rover.ebay.com/rover/1/711-53200-19255-0/1?campid=5336393622&toolid=10013&customId=advertising/tins&mpre=http://www.ebay.com/itm/121856859495","meta":{"price":11200,"date":{"formatted":"2016-01-14T08:00:00.000Z","origin":"-14 hours ago"},"bids":6,"watchers":17},"src":{"original":"http://thumbs4.ebaystatic.com/m/m4Jz4apDifNtzkKdZHicHPg/140.jpg","local":"2016/01/14/9loc/t.jpg"},"images":{"original":["http://i.ebayimg.com/images/g/wVEAAOSwT~9Witbk/s-l64.jpg","http://i.ebayimg.com/images/g/4XoAAOSwL7VWitbu/s-l64.jpg","http://i.ebayimg.com/images/g/hjUAAOSwZG9Witb0/s-l64.jpg","http://i.ebayimg.com/images/g/MB4AAOSw5dNWitb4/s-l64.jpg","http://i.ebayimg.com/images/g/EXEAAOSwwPhWitcA/s-l64.jpg","http://i.ebayimg.com/images/g/xSAAAOSwT~9WitcF/s-l64.jpg","http://i.ebayimg.com/images/g/z4oAAOSwaA5WitcK/s-l64.jpg"],"local":["2016/01/14/9loc/i_0.jpg","2016/01/14/9loc/i_1.jpg","2016/01/14/9loc/i_2.jpg","2016/01/14/9loc/i_3.jpg","2016/01/14/9loc/i_4.jpg","2016/01/14/9loc/i_5.jpg","2016/01/14/9loc/i_6.jpg"]}},{"id":"xxqf","title":"Vintage 1lb Weideman Boy Brand Coffee Tin Cute Graphics & Scenic Graphics Too ","link":"http://rover.ebay.com/rover/1/711-53200-19255-0/1?campid=5336393622&toolid=10013&customId=advertising/tins&mpre=http://www.ebay.com/itm/121857473047","meta":{"price":10907,"date":{"formatted":"2016-01-14T08:00:00.000Z","origin":"-14 hours ago"},"bids":16,"watchers":19},"src":{"original":"http://thumbs4.ebaystatic.com/m/m3Oc2FcXEYRuELLAVP77Mng/140.jpg","local":"2016/01/14/xxqf/t.jpg"},"images":{"original":["http://i.ebayimg.com/images/g/534AAOSwFqJWi~Dl/s-l64.jpg","http://i.ebayimg.com/images/g/5BcAAOSwJkJWi~Dh/s-l64.jpg","http://i.ebayimg.com/images/g/2IMAAOSwHaBWi~Dc/s-l64.jpg","http://i.ebayimg.com/images/g/JfgAAOSwL7VWi~Dq/s-l64.jpg","http://i.ebayimg.com/images/g/6KoAAOSwFqJWi~Du/s-l64.jpg","http://i.ebayimg.com/images/g/5h0AAOSwJkJWi~Dy/s-l64.jpg","http://i.ebayimg.com/images/g/5vwAAOSwJkJWi~D4/s-l64.jpg"],"local":["2016/01/14/xxqf/i_0.jpg","2016/01/14/xxqf/i_1.jpg","2016/01/14/xxqf/i_2.jpg","2016/01/14/xxqf/i_3.jpg","2016/01/14/xxqf/i_4.jpg","2016/01/14/xxqf/i_5.jpg","2016/01/14/xxqf/i_6.jpg"]}},{"id":"e1js","title":"Vintage Potato Chip Tin Rainey's Kriss Kross Philadelphia Pa.","link":"http://rover.ebay.com/rover/1/711-53200-19255-0/1?campid=5336393622&toolid=10013&customId=advertising/tins&mpre=http://www.ebay.com/itm/151941273743","meta":{"price":10000,"date":{"formatted":"2016-01-14T08:00:00.000Z","origin":"-18 hours ago"},"bids":19,"watchers":3},"src":{"original":"http://thumbs4.ebaystatic.com/m/muVTGXvIxDj74psGZKDfFvA/140.jpg","local":"2016/01/14/e1js/t.jpg"},"images":{"original":["http://i.ebayimg.com/images/g/ULgAAOSw5dNWjYDv/s-l300.jpg"],"local":["2016/01/14/e1js/i_0.jpg"]}},{"id":"703z","title":"Rare Mid 20th Century Zig Zag White Rolling Papers Tobacco Dispenser Tin Sign","link":"http://rover.ebay.com/rover/1/711-53200-19255-0/1?campid=5336393622&toolid=10013&customId=advertising/tins&mpre=http://www.ebay.com/itm/281902994385","meta":{"price":8900,"date":{"formatted":"2016-01-14T08:00:00.000Z","origin":"-12 hours ago"},"bids":12,"watchers":25},"src":{"original":"http://thumbs2.ebaystatic.com/m/mzmO3R8wRZu2gIlgEiaccsw/140.jpg","local":"2016/01/14/703z/t.jpg"},"images":{"original":["http://i.ebayimg.com/images/g/VC4AAOSwL7VWjdh5/s-l64.jpg","http://i.ebayimg.com/images/g/Nf8AAOSwwPhWjdRD/s-l64.jpg","http://i.ebayimg.com/images/g/kToAAOSwHnFVtstT/s-l64.jpg","http://i.ebayimg.com/images/g/kjIAAOSwHnFVtstc/s-l64.jpg","http://i.ebayimg.com/images/g/k5kAAOSwHnFVtstp/s-l64.jpg","http://i.ebayimg.com/images/g/z5cAAOSwDNdVtstx/s-l64.jpg","http://i.ebayimg.com/images/g/KVgAAOSwgQ9Vtst3/s-l64.jpg","http://i.ebayimg.com/images/g/034AAOSw9N1VtsuH/s-l64.jpg"],"local":["2016/01/14/703z/i_0.jpg","2016/01/14/703z/i_1.jpg","2016/01/14/703z/i_2.jpg","2016/01/14/703z/i_3.jpg","2016/01/14/703z/i_4.jpg","2016/01/14/703z/i_5.jpg","2016/01/14/703z/i_6.jpg","2016/01/14/703z/i_7.jpg"]}},{"id":"nxd5","title":"Vintage 1930's Mcmahan & Leib Royal Star Coffee Tin Can Anderson Marion, Indiana","link":"http://rover.ebay.com/rover/1/711-53200-19255-0/1?campid=5336393622&toolid=10013&customId=advertising/tins&mpre=http://www.ebay.com/itm/131694958123","meta":{"price":8900,"date":{"formatted":"2016-01-14T08:00:00.000Z","origin":"-3 hours ago"},"bids":13,"watchers":6},"src":{"original":"http://thumbs4.ebaystatic.com/m/mx8QVA6mnitN5Fz_CYBWp0A/140.jpg","local":"2016/01/14/nxd5/t.jpg"},"images":{"original":["http://i.ebayimg.com/images/g/YasAAOSwSHZWgfxE/s-l64.jpg","http://i.ebayimg.com/images/g/m-cAAOSwNyFWgfxb/s-l64.jpg","http://i.ebayimg.com/images/g/YjQAAOSwhkRWgfx0/s-l64.jpg"],"local":["2016/01/14/nxd5/i_0.jpg","2016/01/14/nxd5/i_1.jpg","2016/01/14/nxd5/i_2.jpg"]}},{"id":"30jw","title":"19thc Pastime Plug Tobacco Advertising 10lb Store Display Tin W Litho Labels","link":"http://rover.ebay.com/rover/1/711-53200-19255-0/1?campid=5336393622&toolid=10013&customId=advertising/tins&mpre=http://www.ebay.com/itm/311518547743","meta":{"price":7889,"date":{"formatted":"2016-01-14T08:00:00.000Z","origin":"-11 hours ago"},"bids":8,"watchers":18},"src":{"original":"http://thumbs4.ebaystatic.com/m/m4wqKqkAX2_QTJJSD7uuY4g/140.jpg","local":"2016/01/14/30jw/t.jpg"},"images":{"original":["http://i.ebayimg.com/images/g/6gwAAOSwwPhWjAA~/s-l64.jpg","http://i.ebayimg.com/images/g/7oIAAOSwL7VWjABv/s-l64.jpg","http://i.ebayimg.com/images/g/NYMAAOSwKtlWjABM/s-l64.jpg","http://i.ebayimg.com/images/g/O4wAAOSwKtlWjAB6/s-l64.jpg","http://i.ebayimg.com/images/g/qIIAAOSwZG9WjABY/s-l64.jpg"],"local":["2016/01/14/30jw/i_0.jpg","2016/01/14/30jw/i_1.jpg","2016/01/14/30jw/i_2.jpg","2016/01/14/30jw/i_3.jpg","2016/01/14/30jw/i_4.jpg"]}},{"id":"oiyd","title":"Vintage 1920's 1 Lb. Jefferson Park Coffee Tin With Great Horse Racing Graphics.","link":"http://rover.ebay.com/rover/1/711-53200-19255-0/1?campid=5336393622&toolid=10013&customId=advertising/tins&mpre=http://www.ebay.com/itm/121858338029","meta":{"price":7800,"date":{"formatted":"2016-01-14T08:00:00.000Z","origin":"-14 hours ago"},"bids":7,"watchers":18},"src":{"original":"http://thumbs2.ebaystatic.com/m/mBiowR8-eMr914gMXHl3xUg/140.jpg","local":"2016/01/14/oiyd/t.jpg"},"images":{"original":["http://i.ebayimg.com/images/g/V1wAAOSwoydWjVrV/s-l64.jpg","http://i.ebayimg.com/images/g/A8sAAOSwKtlWjVrZ/s-l64.jpg","http://i.ebayimg.com/images/g/WHsAAOSwoydWjVrd/s-l64.jpg","http://i.ebayimg.com/images/g/j1AAAOSwa-dWjVri/s-l64.jpg","http://i.ebayimg.com/images/g/GxYAAOSwFqJWjVrm/s-l64.jpg","http://i.ebayimg.com/images/g/EhoAAOSwaA5WjVrs/s-l64.jpg","http://i.ebayimg.com/images/g/Ws4AAOSwoydWjVrw/s-l64.jpg"],"local":["2016/01/14/oiyd/i_0.jpg","2016/01/14/oiyd/i_1.jpg","2016/01/14/oiyd/i_2.jpg","2016/01/14/oiyd/i_3.jpg","2016/01/14/oiyd/i_4.jpg","2016/01/14/oiyd/i_5.jpg","2016/01/14/oiyd/i_6.jpg"]}},{"id":"8jdh","title":"Rare Vintage Lays Potato Chip Tin Can Large 3lb Dallas Texas Frito-lay,inc.","link":"http://rover.ebay.com/rover/1/711-53200-19255-0/1?campid=5336393622&toolid=10013&customId=advertising/tins&mpre=http://www.ebay.com/itm/111867803839","meta":{"price":6500,"date":{"formatted":"2016-01-14T08:00:00.000Z","origin":"-20 hours ago"},"bids":19,"watchers":15},"src":{"original":"http://thumbs4.ebaystatic.com/m/mQJH9vgCmWul57U_1yYTspA/140.jpg","local":"2016/01/14/8jdh/t.jpg"},"images":{"original":["http://i.ebayimg.com/images/g/DSoAAOSwGotWjWcn/s-l64.jpg","http://i.ebayimg.com/images/g/X8YAAOSwX~dWjWcz/s-l64.jpg","http://i.ebayimg.com/images/g/c8wAAOSwYIhWjWc-/s-l64.jpg","http://i.ebayimg.com/images/g/dSkAAOSwYIhWjWdN/s-l64.jpg","http://i.ebayimg.com/images/g/dYAAAOSwT~9WjWdk/s-l64.jpg","http://i.ebayimg.com/images/g/Z30AAOSwX~dWjWdx/s-l64.jpg","http://i.ebayimg.com/images/g/cZYAAOSwFqJWjWeH/s-l64.jpg","http://i.ebayimg.com/images/g/eWAAAOSw5dNWjWeT/s-l64.jpg"],"local":["2016/01/14/8jdh/i_0.jpg","2016/01/14/8jdh/i_1.jpg","2016/01/14/8jdh/i_2.jpg","2016/01/14/8jdh/i_3.jpg","2016/01/14/8jdh/i_4.jpg","2016/01/14/8jdh/i_5.jpg","2016/01/14/8jdh/i_6.jpg","2016/01/14/8jdh/i_7.jpg"]}},{"id":"banl","title":"Old Diminutive 4 Ozs Bunte Marshmallows Bunte Bros Chicago Advertising Tin","link":"http://rover.ebay.com/rover/1/711-53200-19255-0/1?campid=5336393622&toolid=10013&customId=advertising/tins&mpre=http://www.ebay.com/itm/151943607348","meta":{"price":5107,"date":{"formatted":"2016-01-14T08:00:00.000Z","origin":"-21 hours ago"},"bids":5,"watchers":10},"src":{"original":"http://thumbs1.ebaystatic.com/m/mufbt04u0jwcX9d4pD2uVPg/140.jpg","local":"2016/01/14/banl/t.jpg"},"images":{"original":["http://i.ebayimg.com/images/g/YDMAAOSwT~9WkAAY/s-l64.jpg","http://i.ebayimg.com/images/g/3kAAAOSwJkJWkAAY/s-l64.jpg","http://i.ebayimg.com/images/g/QSAAAOSwoydWkAAW/s-l64.jpg","http://i.ebayimg.com/images/g/uZoAAOSwGotWkAAZ/s-l64.jpg","http://i.ebayimg.com/images/g/ZGgAAOSwX~dWkAAe/s-l64.jpg","http://i.ebayimg.com/images/g/uj4AAOSwGotWkAAg/s-l64.jpg","http://i.ebayimg.com/images/g/QfoAAOSwoydWkAAg/s-l64.jpg","http://i.ebayimg.com/images/g/hzEAAOSw5dNWkAAh/s-l64.jpg","http://i.ebayimg.com/images/g/h0UAAOSw5dNWkAAi/s-l64.jpg","http://i.ebayimg.com/images/g/B4sAAOSwYIhWkAAi/s-l64.jpg","http://i.ebayimg.com/images/g/W4cAAOSwaA5WkAAY/s-l64.jpg","http://i.ebayimg.com/images/g/WpkAAOSwHaBWkAAY/s-l64.jpg"],"local":["2016/01/14/banl/i_0.jpg","2016/01/14/banl/i_1.jpg","2016/01/14/banl/i_2.jpg","2016/01/14/banl/i_3.jpg","2016/01/14/banl/i_4.jpg","2016/01/14/banl/i_5.jpg","2016/01/14/banl/i_6.jpg","2016/01/14/banl/i_7.jpg","2016/01/14/banl/i_8.jpg","2016/01/14/banl/i_9.jpg","2016/01/14/banl/i_10.jpg","2016/01/14/banl/i_11.jpg"]}},{"id":"q4b7","title":"Nabob Coffee Tin, 5 Pound Size, Green & Red, Vancouver, Canada","link":"http://rover.ebay.com/rover/1/711-53200-19255-0/1?campid=5336393622&toolid=10013&customId=advertising/tins&mpre=http://www.ebay.com/itm/401050100256","meta":{"price":4999,"date":{"formatted":"2016-01-14T08:00:00.000Z","origin":"-15 hours ago"},"bids":2,"watchers":8},"src":{"original":"http://thumbs1.ebaystatic.com/m/myZeLCXkWpMArHmdwVdHGHA/140.jpg","local":"2016/01/14/q4b7/t.jpg"},"images":{"original":["http://i.ebayimg.com/images/g/qocAAOSwHaBWib1~/s-l64.jpg","http://i.ebayimg.com/images/g/It4AAOSwGotWib15/s-l64.jpg","http://i.ebayimg.com/images/g/kRoAAOSwL7VWib2K/s-l64.jpg","http://i.ebayimg.com/images/g/-LUAAOSwZG9Wib2F/s-l64.jpg","http://i.ebayimg.com/images/g/fu8AAOSwX~dWib2S/s-l64.jpg","http://i.ebayimg.com/images/g/DHIAAOSwaA5Wib2f/s-l64.jpg","http://i.ebayimg.com/images/g/jn4AAOSwwPhWib2X/s-l64.jpg"],"local":["2016/01/14/q4b7/i_0.jpg","2016/01/14/q4b7/i_1.jpg","2016/01/14/q4b7/i_2.jpg","2016/01/14/q4b7/i_3.jpg","2016/01/14/q4b7/i_4.jpg","2016/01/14/q4b7/i_5.jpg","2016/01/14/q4b7/i_6.jpg"]}},{"id":"ho6h","title":"Disneyland Snow White Candy Tin Mickey Mouse Minnie Goofy Daffy Duck Pluto","link":"http://rover.ebay.com/rover/1/711-53200-19255-0/1?campid=5336393622&toolid=10013&customId=advertising/tins&mpre=http://www.ebay.com/itm/221987675903","meta":{"price":4900,"date":{"formatted":"2016-01-14T08:00:00.000Z","origin":"-20 hours ago"},"bids":1,"watchers":3},"src":{"original":"http://thumbs4.ebaystatic.com/m/me_G4uCpChLlqaUV2FqkwMg/140.jpg","local":"2016/01/14/ho6h/t.jpg"},"images":{"original":["http://i.ebayimg.com/images/g/v40AAOSwNphWbjoP/s-l64.jpg","http://i.ebayimg.com/images/g/NWcAAOSw8-tWbjoT/s-l64.jpg","http://i.ebayimg.com/images/g/OHgAAOSwwE5WbjoW/s-l64.jpg","http://i.ebayimg.com/images/g/ZlAAAOSwf-VWbjoa/s-l64.jpg","http://i.ebayimg.com/images/g/I34AAOSwcOFWbjod/s-l64.jpg","http://i.ebayimg.com/images/g/wI0AAOSwNphWbjof/s-l64.jpg","http://i.ebayimg.com/images/g/daUAAOSwp5JWbjoh/s-l64.jpg","http://i.ebayimg.com/images/g/I~0AAOSwAKxWbjoj/s-l64.jpg","http://i.ebayimg.com/images/g/deAAAOSwp5JWbjol/s-l64.jpg","http://i.ebayimg.com/images/g/ZywAAOSwf-VWbjoq/s-l64.jpg"],"local":["2016/01/14/ho6h/i_0.jpg","2016/01/14/ho6h/i_1.jpg","2016/01/14/ho6h/i_2.jpg","2016/01/14/ho6h/i_3.jpg","2016/01/14/ho6h/i_4.jpg","2016/01/14/ho6h/i_5.jpg","2016/01/14/ho6h/i_6.jpg","2016/01/14/ho6h/i_7.jpg","2016/01/14/ho6h/i_8.jpg","2016/01/14/ho6h/i_9.jpg"]}},{"id":"ut8c","title":"Log Cabin Syrup Tin Express Office","link":"http://rover.ebay.com/rover/1/711-53200-19255-0/1?campid=5336393622&toolid=10013&customId=advertising/tins&mpre=http://www.ebay.com/itm/221987682691","meta":{"price":4500,"date":{"formatted":"2016-01-14T08:00:00.000Z","origin":"-20 hours ago"},"bids":2,"watchers":3},"src":{"original":"http://thumbs4.ebaystatic.com/m/miWfSJ3rLIL2duKLvvF97cg/140.jpg","local":"2016/01/14/ut8c/t.jpg"},"images":{"original":["http://i.ebayimg.com/images/g/lDIAAOSwv-NWaO1I/s-l64.jpg","http://i.ebayimg.com/images/g/gRsAAOSwnH1WaO1P/s-l64.jpg","http://i.ebayimg.com/images/g/UnwAAOSwcBhWaO1S/s-l64.jpg","http://i.ebayimg.com/images/g/Qf8AAOSwNphWaO1U/s-l64.jpg","http://i.ebayimg.com/images/g/nEwAAOSwnipWaO1W/s-l64.jpg","http://i.ebayimg.com/images/g/ypYAAOSw7FRWaO1Y/s-l64.jpg","http://i.ebayimg.com/images/g/GVoAAOSwbdpWaO1a/s-l64.jpg"],"local":["2016/01/14/ut8c/i_0.jpg","2016/01/14/ut8c/i_1.jpg","2016/01/14/ut8c/i_2.jpg","2016/01/14/ut8c/i_3.jpg","2016/01/14/ut8c/i_4.jpg","2016/01/14/ut8c/i_5.jpg","2016/01/14/ut8c/i_6.jpg"]}},{"id":"qrie","title":"Vintage Woodfields Fish & Oyster Co. Galesville Md Oyster Can With Lid","link":"http://rover.ebay.com/rover/1/711-53200-19255-0/1?campid=5336393622&toolid=10013&customId=advertising/tins&mpre=http://www.ebay.com/itm/262227127964","meta":{"price":4300,"date":{"formatted":"2016-01-14T08:00:00.000Z","origin":"-24 hours ago"},"bids":3,"watchers":2},"src":{"original":"http://thumbs1.ebaystatic.com/m/mphuG-V0pa6mMx69eX94Z4Q/140.jpg","local":"2016/01/14/qrie/t.jpg"},"images":{"original":["http://i.ebayimg.com/images/g/PRsAAOSwaA5WjTdB/s-l64.jpg","http://i.ebayimg.com/images/g/EI4AAOSwGotWjTcs/s-l64.jpg","http://i.ebayimg.com/images/g/x9UAAOSwX~dWjTc2/s-l64.jpg","http://i.ebayimg.com/images/g/ME4AAOSwLN5WjTch/s-l64.jpg"],"local":["2016/01/14/qrie/i_0.jpg","2016/01/14/qrie/i_1.jpg","2016/01/14/qrie/i_2.jpg","2016/01/14/qrie/i_3.jpg"]}},{"id":"w2sh","title":"Rare Vintage Clubb's English Mixture Tobacco Tin Toronto Paper Label","link":"http://rover.ebay.com/rover/1/711-53200-19255-0/1?campid=5336393622&toolid=10013&customId=advertising/tins&mpre=http://www.ebay.com/itm/262228011010","meta":{"price":4200,"date":{"formatted":"2016-01-14T08:00:00.000Z","origin":"-13 hours ago"},"bids":14,"watchers":9},"src":{"original":"http://thumbs3.ebaystatic.com/m/mm_FdPEbKZBQm33l4hvFatQ/140.jpg","local":"2016/01/14/w2sh/t.jpg"},"images":{"original":["http://i.ebayimg.com/images/g/oDIAAOSwT~9Wjaw3/s-l64.jpg","http://i.ebayimg.com/images/g/YWwAAOSwKtlWjaw8/s-l64.jpg","http://i.ebayimg.com/images/g/U1MAAOSwa-dWjaxA/s-l64.jpg","http://i.ebayimg.com/images/g/oZUAAOSwT~9WjaxH/s-l64.jpg","http://i.ebayimg.com/images/g/jqoAAOSwLN5WjaxO/s-l64.jpg","http://i.ebayimg.com/images/g/sXkAAOSw5dNWjaxT/s-l64.jpg"],"local":["2016/01/14/w2sh/i_0.jpg","2016/01/14/w2sh/i_1.jpg","2016/01/14/w2sh/i_2.jpg","2016/01/14/w2sh/i_3.jpg","2016/01/14/w2sh/i_4.jpg","2016/01/14/w2sh/i_5.jpg"]}},{"id":"rtty","title":"Vintage 1lb Weideman Boy Brand Coffee Tin With Great 1920's Art Deco Graphics ","link":"http://rover.ebay.com/rover/1/711-53200-19255-0/1?campid=5336393622&toolid=10013&customId=advertising/tins&mpre=http://www.ebay.com/itm/121858264695","meta":{"price":4198,"date":{"formatted":"2016-01-14T08:00:00.000Z","origin":"-14 hours ago"},"bids":2,"watchers":5},"src":{"original":"http://thumbs4.ebaystatic.com/m/msv_DH9eB3VNYGmE2AIWfpQ/140.jpg","local":"2016/01/14/rtty/t.jpg"},"images":{"original":["http://i.ebayimg.com/images/g/E0YAAOSw5dNWjUEd/s-l64.jpg","http://i.ebayimg.com/images/g/uHkAAOSwL7VWjUEf/s-l64.jpg","http://i.ebayimg.com/images/g/HdMAAOSwGotWjUEj/s-l64.jpg","http://i.ebayimg.com/images/g/FBsAAOSw5dNWjUEm/s-l64.jpg","http://i.ebayimg.com/images/g/uWYAAOSwL7VWjUEq/s-l64.jpg","http://i.ebayimg.com/images/g/HrsAAOSwGotWjUEt/s-l64.jpg","http://i.ebayimg.com/images/g/MLsAAOSwT~9WjUE0/s-l64.jpg"],"local":["2016/01/14/rtty/i_0.jpg","2016/01/14/rtty/i_1.jpg","2016/01/14/rtty/i_2.jpg","2016/01/14/rtty/i_3.jpg","2016/01/14/rtty/i_4.jpg","2016/01/14/rtty/i_5.jpg","2016/01/14/rtty/i_6.jpg"]}},{"id":"eeov","title":"Tobacco Tin Charles Rattray's Hal O' The Wynd","link":"http://rover.ebay.com/rover/1/711-53200-19255-0/1?campid=5336393622&toolid=10013&customId=advertising/tins&mpre=http://www.ebay.com/itm/111867534221","meta":{"price":4005,"date":{"formatted":"2016-01-14T08:00:00.000Z","origin":"-13 hours ago"},"bids":8,"watchers":21},"src":{"original":"http://thumbs2.ebaystatic.com/m/m6G8GyOE6LtUsnJ6u0rcXzg/140.jpg","local":"2016/01/14/eeov/t.jpg"},"images":{"original":["http://i.ebayimg.com/images/g/51EAAOSwT~9WjQFl/s-l64.jpg","http://i.ebayimg.com/images/g/57MAAOSwT~9WjQFq/s-l64.jpg","http://i.ebayimg.com/images/g/7KIAAOSwYIhWjQFr/s-l64.jpg","http://i.ebayimg.com/images/g/mJIAAOSwJkJWjQFr/s-l64.jpg","http://i.ebayimg.com/images/g/mz8AAOSwX~dWjQFx/s-l64.jpg","http://i.ebayimg.com/images/g/Lc8AAOSwLN5WjQFy/s-l64.jpg","http://i.ebayimg.com/images/g/WGoAAOSwaA5WjQFz/s-l64.jpg","http://i.ebayimg.com/images/g/n4QAAOSwwPhWjQF0/s-l64.jpg","http://i.ebayimg.com/images/g/HpQAAOSwL7VWjQF2/s-l64.jpg","http://i.ebayimg.com/images/g/JMEAAOSwa-dWjQF3/s-l64.jpg","http://i.ebayimg.com/images/g/zP0AAOSwoydWjQF4/s-l64.jpg"],"local":["2016/01/14/eeov/i_0.jpg","2016/01/14/eeov/i_1.jpg","2016/01/14/eeov/i_2.jpg","2016/01/14/eeov/i_3.jpg","2016/01/14/eeov/i_4.jpg","2016/01/14/eeov/i_5.jpg","2016/01/14/eeov/i_6.jpg","2016/01/14/eeov/i_7.jpg","2016/01/14/eeov/i_8.jpg","2016/01/14/eeov/i_9.jpg","2016/01/14/eeov/i_10.jpg"]}},{"id":"jay0","title":"Vintage Chas Neubert & Co. Baltimore Maryland Mermaid Oyster Can Advertising Tin","link":"http://rover.ebay.com/rover/1/711-53200-19255-0/1?campid=5336393622&toolid=10013&customId=advertising/tins&mpre=http://www.ebay.com/itm/331748257699","meta":{"price":4000,"date":{"formatted":"2016-01-14T08:00:00.000Z","origin":"-20 hours ago"},"bids":8,"watchers":11},"src":{"original":"http://thumbs4.ebaystatic.com/m/mxcfksVW8fhVOXQxs4l5f7A/140.jpg","local":"2016/01/14/jay0/t.jpg"},"images":{"original":["http://i.ebayimg.com/images/g/OMcAAOSwYIhWjW5E/s-l64.jpg","http://i.ebayimg.com/images/g/VWAAAOSwLN5WjW5I/s-l64.jpg","http://i.ebayimg.com/images/g/3JIAAOSwa-dWjW5N/s-l64.jpg","http://i.ebayimg.com/images/g/VrIAAOSwLN5WjW5S/s-l64.jpg","http://i.ebayimg.com/images/g/OzsAAOSwYIhWjW5W/s-l64.jpg","http://i.ebayimg.com/images/g/yf4AAOSwZG9WjW5b/s-l64.jpg","http://i.ebayimg.com/images/g/yoAAAOSwZG9WjW5f/s-l64.jpg"],"local":["2016/01/14/jay0/i_0.jpg","2016/01/14/jay0/i_1.jpg","2016/01/14/jay0/i_2.jpg","2016/01/14/jay0/i_3.jpg","2016/01/14/jay0/i_4.jpg","2016/01/14/jay0/i_5.jpg","2016/01/14/jay0/i_6.jpg"]}},{"id":"wimz","title":"Early Litho Colonial Malt Milk Crackers Gen Store Counter Tin - Pittsburgh, Pa ","link":"http://rover.ebay.com/rover/1/711-53200-19255-0/1?campid=5336393622&toolid=10013&customId=advertising/tins&mpre=http://www.ebay.com/itm/252240059996","meta":{"price":4000,"date":{"formatted":"2016-01-14T08:00:00.000Z","origin":"-24 hours ago"},"bids":1,"watchers":1},"src":{"original":"http://thumbs1.ebaystatic.com/m/m3xfrpejp_eLWbK1OW73gYA/140.jpg","local":"2016/01/14/wimz/t.jpg"},"images":{"original":["http://i.ebayimg.com/images/g/7ioAAOSwaA5WjSvI/s-l64.jpg","http://i.ebayimg.com/images/g/3OIAAOSwLN5WjSvP/s-l64.jpg","http://i.ebayimg.com/images/g/V40AAOSwwPhWjSvW/s-l64.jpg","http://i.ebayimg.com/images/g/3QIAAOSwGotWjSvd/s-l64.jpg","http://i.ebayimg.com/images/g/LO0AAOSwKtlWjSvk/s-l64.jpg","http://i.ebayimg.com/images/g/8qMAAOSwaA5WjSvq/s-l64.jpg","http://i.ebayimg.com/images/g/c3AAAOSwX~dWjSv3/s-l64.jpg","http://i.ebayimg.com/images/g/9PUAAOSwaA5WjSv-/s-l64.jpg","http://i.ebayimg.com/images/g/fB4AAOSwL7VWjSwE/s-l64.jpg","http://i.ebayimg.com/images/g/lYIAAOSwHaBWjSwK/s-l64.jpg"],"local":["2016/01/14/wimz/i_0.jpg","2016/01/14/wimz/i_1.jpg","2016/01/14/wimz/i_2.jpg","2016/01/14/wimz/i_3.jpg","2016/01/14/wimz/i_4.jpg","2016/01/14/wimz/i_5.jpg","2016/01/14/wimz/i_6.jpg","2016/01/14/wimz/i_7.jpg","2016/01/14/wimz/i_8.jpg","2016/01/14/wimz/i_9.jpg"]}},{"id":"vsym","title":"Vintage Cracker Jack Tin Litho Toy Whistle Old Prize ","link":"http://rover.ebay.com/rover/1/711-53200-19255-0/1?campid=5336393622&toolid=10013&customId=advertising/tins&mpre=http://www.ebay.com/itm/181983947779","meta":{"price":3499,"date":{"formatted":"2016-01-14T08:00:00.000Z","origin":"-10 hours ago"},"bids":2,"watchers":1},"src":{"original":"http://thumbs4.ebaystatic.com/m/mhMY_V30L2z6f71MT5EinlQ/140.jpg","local":"2016/01/14/vsym/t.jpg"},"images":{"original":["http://i.ebayimg.com/images/g/xdUAAOSw7FRWVo-S/s-l64.jpg","http://i.ebayimg.com/images/g/Zx0AAOSwcBhWVo-0/s-l64.jpg"],"local":["2016/01/14/vsym/i_0.jpg","2016/01/14/vsym/i_1.jpg"]}},{"id":"701u","title":"Antique American Coffee Tin Acme Brand For The American Stores, Phila.,c 1920 ","link":"http://rover.ebay.com/rover/1/711-53200-19255-0/1?campid=5336393622&toolid=10013&customId=advertising/tins&mpre=http://www.ebay.com/itm/131694661463","meta":{"price":3282,"date":{"formatted":"2016-01-14T08:00:00.000Z","origin":"-12 hours ago"},"bids":5,"watchers":6},"src":{"original":"http://thumbs4.ebaystatic.com/m/mevJnAG-H2xK6yNOweua2xA/140.jpg","local":"2016/01/14/701u/t.jpg"},"images":{"original":["http://i.ebayimg.com/images/g/ghQAAOSwGotWjdW3/s-l64.jpg","http://i.ebayimg.com/images/g/OZgAAOSwaA5WjdXR/s-l64.jpg","http://i.ebayimg.com/images/g/PXMAAOSwFqJWjdXs/s-l64.jpg","http://i.ebayimg.com/images/g/A7wAAOSwZG9WjdYE/s-l64.jpg","http://i.ebayimg.com/images/g/pagAAOSwLN5WjdYe/s-l64.jpg","http://i.ebayimg.com/images/g/L~4AAOSwL7VWjdY5/s-l64.jpg"],"local":["2016/01/14/701u/i_0.jpg","2016/01/14/701u/i_1.jpg","2016/01/14/701u/i_2.jpg","2016/01/14/701u/i_3.jpg","2016/01/14/701u/i_4.jpg","2016/01/14/701u/i_5.jpg"]}},{"id":"3l7o","title":"Vintage Retro Kahn's American Beauty Pure Lard Tin Can Bale Handle Cincinnati","link":"http://rover.ebay.com/rover/1/711-53200-19255-0/1?campid=5336393622&toolid=10013&customId=advertising/tins&mpre=http://www.ebay.com/itm/321966177707","meta":{"price":3250,"date":{"formatted":"2016-01-14T08:00:00.000Z","origin":"-13 hours ago"},"bids":4,"watchers":11},"src":{"original":"http://thumbs4.ebaystatic.com/m/m2bvXFkz6b5Ol-_VSKCoQiw/140.jpg","local":"2016/01/14/3l7o/t.jpg"},"images":{"original":["http://i.ebayimg.com/images/g/FrMAAOSwNyFWfEbj/s-l64.jpg","http://i.ebayimg.com/images/g/MOAAAOSwYaFWfEb6/s-l64.jpg","http://i.ebayimg.com/images/g/0c0AAOSwk1JWfEcd/s-l64.jpg","http://i.ebayimg.com/images/g/kUMAAOSwo3pWfEc2/s-l64.jpg","http://i.ebayimg.com/images/g/N~IAAOSwYaFWfEdd/s-l64.jpg"],"local":["2016/01/14/3l7o/i_0.jpg","2016/01/14/3l7o/i_1.jpg","2016/01/14/3l7o/i_2.jpg","2016/01/14/3l7o/i_3.jpg","2016/01/14/3l7o/i_4.jpg"]}},{"id":"ipz4","title":"Vintage 1920's Art Deco Pola Negri Silent Movie Candy Tin Beautebox Canco","link":"http://rover.ebay.com/rover/1/711-53200-19255-0/1?campid=5336393622&toolid=10013&customId=advertising/tins&mpre=http://www.ebay.com/itm/131696094254","meta":{"price":3200,"date":{"formatted":"2016-01-14T08:00:00.000Z","origin":"-21 hours ago"},"bids":2,"watchers":8},"src":{"original":"http://thumbs3.ebaystatic.com/m/mzBB9MTloEwhjoqvvOSKvNg/140.jpg","local":"2016/01/14/ipz4/t.jpg"},"images":{"original":["http://i.ebayimg.com/images/g/6s0AAOSwGotWkAIT/s-l64.jpg","http://i.ebayimg.com/images/g/dTUAAOSwoydWkAIZ/s-l64.jpg","http://i.ebayimg.com/images/g/nAIAAOSwwPhWkAIe/s-l64.jpg","http://i.ebayimg.com/images/g/tBQAAOSwL7VWkAIo/s-l64.jpg","http://i.ebayimg.com/images/g/P2cAAOSwKtlWkAIt/s-l64.jpg","http://i.ebayimg.com/images/g/nAQAAOSwaA5WkAI2/s-l64.jpg"],"local":["2016/01/14/ipz4/i_0.jpg","2016/01/14/ipz4/i_1.jpg","2016/01/14/ipz4/i_2.jpg","2016/01/14/ipz4/i_3.jpg","2016/01/14/ipz4/i_4.jpg","2016/01/14/ipz4/i_5.jpg"]}},{"id":"cw1w","title":"Vintage Earl Cockrell Oysters 1 Gal. Embossed Metal Can, Burgess Va.183","link":"http://rover.ebay.com/rover/1/711-53200-19255-0/1?campid=5336393622&toolid=10013&customId=advertising/tins&mpre=http://www.ebay.com/itm/371527732125","meta":{"price":3200,"date":{"formatted":"2016-01-14T08:00:00.000Z","origin":"-14 hours ago"},"bids":2,"watchers":6},"src":{"original":"http://thumbs2.ebaystatic.com/m/mxT0rXiWT-itc8LlsF_zZzQ/140.jpg","local":"2016/01/14/cw1w/t.jpg"},"images":{"original":["http://i.ebayimg.com/images/g/t4IAAOSwJcZWeNKZ/s-l64.jpg","http://i.ebayimg.com/images/g/zCcAAOSwSdZWeNJ7/s-l64.jpg","http://i.ebayimg.com/images/g/zroAAOSwCQNWeNKB/s-l64.jpg","http://i.ebayimg.com/images/g/51QAAOSw3KFWeNKI/s-l64.jpg","http://i.ebayimg.com/images/g/zP4AAOSwSdZWeNKM/s-l64.jpg","http://i.ebayimg.com/images/g/LicAAOSw~otWeNKU/s-l64.jpg"],"local":["2016/01/14/cw1w/i_0.jpg","2016/01/14/cw1w/i_1.jpg","2016/01/14/cw1w/i_2.jpg","2016/01/14/cw1w/i_3.jpg","2016/01/14/cw1w/i_4.jpg","2016/01/14/cw1w/i_5.jpg"]}},{"id":"ozia","title":"Vintage 1930's Cracker Jack Tin Litho Ambulance Vehicle Toy Old Charm Very Nice!","link":"http://rover.ebay.com/rover/1/711-53200-19255-0/1?campid=5336393622&toolid=10013&customId=advertising/tins&mpre=http://www.ebay.com/itm/331748278068","meta":{"price":2999,"date":{"formatted":"2016-01-14T08:00:00.000Z","origin":"-19 hours ago"},"bids":1,"watchers":1},"src":{"original":"http://thumbs1.ebaystatic.com/m/mdJ4r85WUja-xzJR8mctm6w/140.jpg","local":"2016/01/14/ozia/t.jpg"},"images":{"original":["http://i.ebayimg.com/images/g/m3EAAOSwHaBWjXcH/s-l64.jpg","http://i.ebayimg.com/images/g/nHIAAOSwHaBWjXcN/s-l64.jpg","http://i.ebayimg.com/images/g/nhQAAOSwHaBWjXcW/s-l64.jpg","http://i.ebayimg.com/images/g/nf4AAOSwHaBWjXcW/s-l64.jpg","http://i.ebayimg.com/images/g/wIYAAOSwZG9WjXch/s-l64.jpg","http://i.ebayimg.com/images/g/IcEAAOSwaA5WjXce/s-l64.jpg"],"local":["2016/01/14/ozia/i_0.jpg","2016/01/14/ozia/i_1.jpg","2016/01/14/ozia/i_2.jpg","2016/01/14/ozia/i_3.jpg","2016/01/14/ozia/i_4.jpg","2016/01/14/ozia/i_5.jpg"]}},{"id":"lsl7","title":"Antique French Lithographic Sewing Tin With Elfs Pfaff Co. C. 1920","link":"http://rover.ebay.com/rover/1/711-53200-19255-0/1?campid=5336393622&toolid=10013&customId=advertising/tins&mpre=http://www.ebay.com/itm/131694563985","meta":{"price":2933,"date":{"formatted":"2016-01-14T08:00:00.000Z","origin":"-16 hours ago"},"bids":7,"watchers":10},"src":{"original":"http://thumbs2.ebaystatic.com/m/mtYYUoKIb2e8JmTk9HTAImA/140.jpg","local":"2016/01/14/lsl7/t.jpg"},"images":{"original":["http://i.ebayimg.com/images/g/DFcAAOSwGotWjaVL/s-l64.jpg","http://i.ebayimg.com/images/g/FiIAAOSw5dNWjaVi/s-l64.jpg","http://i.ebayimg.com/images/g/F~EAAOSw5dNWjaV4/s-l64.jpg","http://i.ebayimg.com/images/g/9y4AAOSwYIhWjaWG/s-l64.jpg","http://i.ebayimg.com/images/g/GfEAAOSw5dNWjaWU/s-l64.jpg","http://i.ebayimg.com/images/g/xTEAAOSwKtlWjaWz/s-l64.jpg"],"local":["2016/01/14/lsl7/i_0.jpg","2016/01/14/lsl7/i_1.jpg","2016/01/14/lsl7/i_2.jpg","2016/01/14/lsl7/i_3.jpg","2016/01/14/lsl7/i_4.jpg","2016/01/14/lsl7/i_5.jpg"]}},{"id":"vydx","title":"Antique Tin Litho Advertising Figural Ceresota Bread Flour Match Holder/safe ","link":"http://rover.ebay.com/rover/1/711-53200-19255-0/1?campid=5336393622&toolid=10013&customId=advertising/tins&mpre=http://www.ebay.com/itm/311519712958","meta":{"price":2800,"date":{"formatted":"2016-01-14T08:00:00.000Z","origin":"-15 hours ago"},"bids":3,"watchers":12},"src":{"original":"http://thumbs3.ebaystatic.com/m/mA9BK-hs18CA-_ZHVH2C2_w/140.jpg","local":"2016/01/14/vydx/t.jpg"},"images":{"original":["http://i.ebayimg.com/images/g/NrMAAOSwZG9Wja6p/s-l300.jpg"],"local":["2016/01/14/vydx/i_0.jpg"]}},{"id":"nye9","title":"Graphic Old B & L Oyster Tin","link":"http://rover.ebay.com/rover/1/711-53200-19255-0/1?campid=5336393622&toolid=10013&customId=advertising/tins&mpre=http://www.ebay.com/itm/191776432887","meta":{"price":2800,"date":{"formatted":"2016-01-14T08:00:00.000Z","origin":"-22 hours ago"},"bids":1,"watchers":2},"src":{"original":"http://thumbs4.ebaystatic.com/m/m85bqUtV77D-KdGU-_BPq5g/140.jpg","local":"2016/01/14/nye9/t.jpg"},"images":{"original":["http://i.ebayimg.com/images/g/Tx8AAOSwT~9WjVQp/s-l64.jpg","http://i.ebayimg.com/images/g/QAAAAOSw5dNWjVQu/s-l64.jpg"],"local":["2016/01/14/nye9/i_0.jpg","2016/01/14/nye9/i_1.jpg"]}},{"id":"xscy","title":"Popcorn Unopened Tin Can; 10 Oz. Bonnie Lee,white Hulless /great Detail Use","link":"http://rover.ebay.com/rover/1/711-53200-19255-0/1?campid=5336393622&toolid=10013&customId=advertising/tins&mpre=http://www.ebay.com/itm/291655988593","meta":{"price":2787,"date":{"formatted":"2016-01-14T08:00:00.000Z","origin":"-13 hours ago"},"bids":2,"watchers":1},"src":{"original":"http://thumbs2.ebaystatic.com/m/mO9EaIVYxyu4sdiLov5r9Sg/140.jpg","local":"2016/01/14/xscy/t.jpg"},"images":{"original":["http://i.ebayimg.com/images/g/NJoAAOSwNyFWd1xw/s-l64.jpg","http://i.ebayimg.com/images/g/dS8AAOSwUdlWd1x4/s-l64.jpg","http://i.ebayimg.com/images/g/ZB0AAOSw3KFWd1yA/s-l64.jpg","http://i.ebayimg.com/images/g/2G4AAOSwCQNWd1yH/s-l64.jpg","http://i.ebayimg.com/images/g/7JkAAOSwYaFWd1yO/s-l64.jpg","http://i.ebayimg.com/images/g/ND8AAOSwSHZWd1yV/s-l64.jpg","http://i.ebayimg.com/images/g/d8gAAOSwUdlWd1yd/s-l64.jpg","http://i.ebayimg.com/images/g/UkIAAOSwo3pWd1ym/s-l64.jpg","http://i.ebayimg.com/images/g/wVoAAOSwSdZWd1yt/s-l64.jpg","http://i.ebayimg.com/images/g/GnMAAOSwhkRWd1y1/s-l64.jpg"],"local":["2016/01/14/xscy/i_0.jpg","2016/01/14/xscy/i_1.jpg","2016/01/14/xscy/i_2.jpg","2016/01/14/xscy/i_3.jpg","2016/01/14/xscy/i_4.jpg","2016/01/14/xscy/i_5.jpg","2016/01/14/xscy/i_6.jpg","2016/01/14/xscy/i_7.jpg","2016/01/14/xscy/i_8.jpg","2016/01/14/xscy/i_9.jpg"]}},{"id":"3fk8","title":"Round 100 No. 6 Atlas Blasting Cap Tin","link":"http://rover.ebay.com/rover/1/711-53200-19255-0/1?campid=5336393622&toolid=10013&customId=advertising/tins&mpre=http://www.ebay.com/itm/262228119576","meta":{"price":2625,"date":{"formatted":"2016-01-14T08:00:00.000Z","origin":"-13 hours ago"},"bids":3,"watchers":6},"src":{"original":"http://thumbs1.ebaystatic.com/m/mt_erRUmLHq5PwxnjKR43ww/140.jpg","local":"2016/01/14/3fk8/t.jpg"},"images":{"original":["http://i.ebayimg.com/images/g/51YAAOSwFqJWjdD6/s-l64.jpg","http://i.ebayimg.com/images/g/5QwAAOSwaA5WjdED/s-l64.jpg","http://i.ebayimg.com/images/g/dqwAAOSwX~dWjdEM/s-l64.jpg","http://i.ebayimg.com/images/g/d3kAAOSwX~dWjdEU/s-l64.jpg","http://i.ebayimg.com/images/g/6d0AAOSwFqJWjdEg/s-l64.jpg","http://i.ebayimg.com/images/g/jKgAAOSw5dNWjdEp/s-l64.jpg","http://i.ebayimg.com/images/g/a68AAOSwKtlWjdEz/s-l64.jpg"],"local":["2016/01/14/3fk8/i_0.jpg","2016/01/14/3fk8/i_1.jpg","2016/01/14/3fk8/i_2.jpg","2016/01/14/3fk8/i_3.jpg","2016/01/14/3fk8/i_4.jpg","2016/01/14/3fk8/i_5.jpg","2016/01/14/3fk8/i_6.jpg"]}},{"id":"4rv5","title":"Antique 1900`s Neverslip Tools/shoes/pads Advertising Tin","link":"http://rover.ebay.com/rover/1/711-53200-19255-0/1?campid=5336393622&toolid=10013&customId=advertising/tins&mpre=http://www.ebay.com/itm/371527482797","meta":{"price":2500,"date":{"formatted":"2016-01-14T08:00:00.000Z","origin":"-15 hours ago"},"bids":8,"watchers":8},"src":{"original":"http://thumbs2.ebaystatic.com/m/mk-lqvC9HWBWLoFohQ7n3fw/140.jpg","local":"2016/01/14/4rv5/t.jpg"},"images":{"original":["http://i.ebayimg.com/images/g/d1gAAOSwHaBWj~FC/s-l64.jpg","http://i.ebayimg.com/images/g/J2UAAOSwJkJWj~FI/s-l64.jpg","http://i.ebayimg.com/images/g/l2oAAOSwwPhWj~E~/s-l64.jpg","http://i.ebayimg.com/images/g/Qg4AAOSwYIhWj~FF/s-l64.jpg"],"local":["2016/01/14/4rv5/i_0.jpg","2016/01/14/4rv5/i_1.jpg","2016/01/14/4rv5/i_2.jpg","2016/01/14/4rv5/i_3.jpg"]}},{"id":"2yrt","title":"Mcclelland 1977-2005 Anniversary Collectible Tin","link":"http://rover.ebay.com/rover/1/711-53200-19255-0/1?campid=5336393622&toolid=10013&customId=advertising/tins&mpre=http://www.ebay.com/itm/262227674751","meta":{"price":2450,"date":{"formatted":"2016-01-14T08:00:00.000Z","origin":"-18 hours ago"},"bids":10,"watchers":11},"src":{"original":"http://thumbs4.ebaystatic.com/m/msqwUkFRQlBmP3E3vkSSGQA/140.jpg","local":"2016/01/14/2yrt/t.jpg"},"images":{"original":["http://i.ebayimg.com/images/g/F8EAAOSw8-tWbcu5/s-l64.jpg","http://i.ebayimg.com/images/g/FTIAAOSwcOFWbcvK/s-l64.jpg","http://i.ebayimg.com/images/g/eb0AAOSwNphWbcvf/s-l64.jpg"],"local":["2016/01/14/2yrt/i_0.jpg","2016/01/14/2yrt/i_1.jpg","2016/01/14/2yrt/i_2.jpg"]}},{"id":"vmxa","title":"Antique Meadow-sweet Peanut Butter Tin Litho Advertising","link":"http://rover.ebay.com/rover/1/711-53200-19255-0/1?campid=5336393622&toolid=10013&customId=advertising/tins&mpre=http://www.ebay.com/itm/381512382892","meta":{"price":2150,"date":{"formatted":"2016-01-14T08:00:00.000Z","origin":"-14 hours ago"},"bids":5,"watchers":8},"src":{"original":"http://thumbs1.ebaystatic.com/m/mLcmtVN1QEVzg0JAySWL4ZA/140.jpg","local":"2016/01/14/vmxa/t.jpg"},"images":{"original":["http://i.ebayimg.com/images/g/1zsAAOSwX~dWjbt5/s-l64.jpg","http://i.ebayimg.com/images/g/I1gAAOSwZG9Wjbt8/s-l64.jpg","http://i.ebayimg.com/images/g/17kAAOSwX~dWjbt~/s-l64.jpg","http://i.ebayimg.com/images/g/1SwAAOSwT~9WjbuC/s-l64.jpg"],"local":["2016/01/14/vmxa/i_0.jpg","2016/01/14/vmxa/i_1.jpg","2016/01/14/vmxa/i_2.jpg","2016/01/14/vmxa/i_3.jpg"]}},{"id":"hdhj","title":"Vintage Pocket Tin Dryback Band-aid Tin 1926 Very Nice Condition","link":"http://rover.ebay.com/rover/1/711-53200-19255-0/1?campid=5336393622&toolid=10013&customId=advertising/tins&mpre=http://www.ebay.com/itm/262227194124","meta":{"price":2150,"date":{"formatted":"2016-01-14T08:00:00.000Z","origin":"-12 hours ago"},"bids":5,"watchers":3},"src":{"original":"http://thumbs1.ebaystatic.com/m/mNmYa-Mp6eQPJ0xvQVeCUFA/140.jpg","local":"2016/01/14/hdhj/t.jpg"},"images":{"original":["http://i.ebayimg.com/images/g/gRcAAOSwL7VWjT7o/s-l64.jpg","http://i.ebayimg.com/images/g/HXQAAOSwaA5WjT7r/s-l64.jpg","http://i.ebayimg.com/images/g/m6wAAOSwKtlWjT7v/s-l64.jpg","http://i.ebayimg.com/images/g/giwAAOSwL7VWjT7z/s-l64.jpg"],"local":["2016/01/14/hdhj/i_0.jpg","2016/01/14/hdhj/i_1.jpg","2016/01/14/hdhj/i_2.jpg","2016/01/14/hdhj/i_3.jpg"]}},{"id":"n0vg","title":"5 Pound Coffee Tin Preto Brand Levering Coffee Co. Vintage ","link":"http://rover.ebay.com/rover/1/711-53200-19255-0/1?campid=5336393622&toolid=10013&customId=advertising/tins&mpre=http://www.ebay.com/itm/231805657835","meta":{"price":2050,"date":{"formatted":"2016-01-14T08:00:00.000Z","origin":"-15 hours ago"},"bids":3,"watchers":4},"src":{"original":"http://thumbs4.ebaystatic.com/m/m2_MtqysD-rBT7U4puH1yFg/140.jpg","local":"2016/01/14/n0vg/t.jpg"},"images":{"original":["http://i.ebayimg.com/images/g/RrEAAOSwL7VWjaCd/s-l64.jpg","http://i.ebayimg.com/images/g/MGkAAOSwHaBWjaCL/s-l64.jpg","http://i.ebayimg.com/images/g/hYwAAOSwYIhWjaB7/s-l64.jpg","http://i.ebayimg.com/images/g/necAAOSw5dNWjaBj/s-l64.jpg","http://i.ebayimg.com/images/g/i2QAAOSwT~9WjaBR/s-l64.jpg","http://i.ebayimg.com/images/g/OZsAAOSwKtlWjaA-/s-l64.jpg","http://i.ebayimg.com/images/g/Pa0AAOSwa-dWjaAp/s-l64.jpg","http://i.ebayimg.com/images/g/Ss0AAOSwoydWjaAR/s-l64.jpg"],"local":["2016/01/14/n0vg/i_0.jpg","2016/01/14/n0vg/i_1.jpg","2016/01/14/n0vg/i_2.jpg","2016/01/14/n0vg/i_3.jpg","2016/01/14/n0vg/i_4.jpg","2016/01/14/n0vg/i_5.jpg","2016/01/14/n0vg/i_6.jpg","2016/01/14/n0vg/i_7.jpg"]}},{"id":"vl5p","title":"Vtg Chrysanthemum English Biscuit Tin Box Chocolate Candy Cookie Cracker Antique","link":"http://rover.ebay.com/rover/1/711-53200-19255-0/1?campid=5336393622&toolid=10013&customId=advertising/tins&mpre=http://www.ebay.com/itm/252240010678","meta":{"price":1999,"date":{"formatted":"2016-01-14T08:00:00.000Z","origin":"-13 hours ago"},"bids":1,"watchers":11},"src":{"original":"http://thumbs3.ebaystatic.com/m/muEroIBykzz0cOlZl3mCvLg/140.jpg","local":"2016/01/14/vl5p/t.jpg"},"images":{"original":["http://i.ebayimg.com/images/g/wuAAAOSwHaBWjR0z/s-l64.jpg","http://i.ebayimg.com/images/g/S4MAAOSwKtlWjR02/s-l64.jpg","http://i.ebayimg.com/images/g/AywAAOSwYIhWjR06/s-l64.jpg","http://i.ebayimg.com/images/g/qG8AAOSwwPhWjR09/s-l64.jpg","http://i.ebayimg.com/images/g/UHMAAOSwGotWjR1H/s-l64.jpg","http://i.ebayimg.com/images/g/4-IAAOSw5dNWjR1M/s-l64.jpg","http://i.ebayimg.com/images/g/uNcAAOSwoydWjR1V/s-l64.jpg","http://i.ebayimg.com/images/g/5aYAAOSw5dNWjR1b/s-l64.jpg","http://i.ebayimg.com/images/g/miIAAOSwJkJWjR1e/s-l64.jpg","http://i.ebayimg.com/images/g/~7EAAOSwT~9WjR1h/s-l64.jpg"],"local":["2016/01/14/vl5p/i_0.jpg","2016/01/14/vl5p/i_1.jpg","2016/01/14/vl5p/i_2.jpg","2016/01/14/vl5p/i_3.jpg","2016/01/14/vl5p/i_4.jpg","2016/01/14/vl5p/i_5.jpg","2016/01/14/vl5p/i_6.jpg","2016/01/14/vl5p/i_7.jpg","2016/01/14/vl5p/i_8.jpg","2016/01/14/vl5p/i_9.jpg"]}},{"id":"mi39","title":"Hudson's Bay Imperial Mixture Small Round Red Tobacco Tin 1897 Excise Label","link":"http://rover.ebay.com/rover/1/711-53200-19255-0/1?campid=5336393622&toolid=10013&customId=advertising/tins&mpre=http://www.ebay.com/itm/141870735976","meta":{"price":1999,"date":{"formatted":"2016-01-14T08:00:00.000Z","origin":"-13 hours ago"},"bids":1,"watchers":4},"src":{"original":"http://thumbs1.ebaystatic.com/m/mxDEB-em7aA2hcJHg3ZYfDw/140.jpg","local":"2016/01/14/mi39/t.jpg"},"images":{"original":["http://i.ebayimg.com/images/g/S-gAAOSwo0JWJtSe/s-l64.jpg","http://i.ebayimg.com/images/g/NIcAAOSwo6lWJtTB/s-l64.jpg","http://i.ebayimg.com/images/g/NywAAOSwAYtWJtTI/s-l64.jpg","http://i.ebayimg.com/images/g/Mt4AAOSwo6lWJtSq/s-l64.jpg","http://i.ebayimg.com/images/g/f84AAOSwhcJWJtTQ/s-l64.jpg"],"local":["2016/01/14/mi39/i_0.jpg","2016/01/14/mi39/i_1.jpg","2016/01/14/mi39/i_2.jpg","2016/01/14/mi39/i_3.jpg","2016/01/14/mi39/i_4.jpg"]}},{"id":"6zqd","title":"Vtg.olive Oil Tin-8oz. Mamma Mia~exquisite Graphics~great Shape~","link":"http://rover.ebay.com/rover/1/711-53200-19255-0/1?campid=5336393622&toolid=10013&customId=advertising/tins&mpre=http://www.ebay.com/itm/131691879809","meta":{"price":1999,"date":{"formatted":"2016-01-14T08:00:00.000Z","origin":"-20 hours ago"},"bids":2,"watchers":2},"src":{"original":"http://thumbs2.ebaystatic.com/m/mDOA9Sill1w45a1_m3CkFDg/140.jpg","local":"2016/01/14/6zqd/t.jpg"},"images":{"original":["http://i.ebayimg.com/images/g/uh8AAOSwHaBWiXci/s-l64.jpg","http://i.ebayimg.com/images/g/qzkAAOSwJkJWiXcn/s-l64.jpg","http://i.ebayimg.com/images/g/vC8AAOSwHaBWiXc0/s-l64.jpg","http://i.ebayimg.com/images/g/XkYAAOSw5dNWiXc3/s-l64.jpg","http://i.ebayimg.com/images/g/AsoAAOSwwPhWiXce/s-l64.jpg","http://i.ebayimg.com/images/g/SS0AAOSwGotWiXcs/s-l64.jpg","http://i.ebayimg.com/images/g/SWMAAOSwGotWiXcv/s-l64.jpg"],"local":["2016/01/14/6zqd/i_0.jpg","2016/01/14/6zqd/i_1.jpg","2016/01/14/6zqd/i_2.jpg","2016/01/14/6zqd/i_3.jpg","2016/01/14/6zqd/i_4.jpg","2016/01/14/6zqd/i_5.jpg","2016/01/14/6zqd/i_6.jpg"]}},{"id":"ntb9","title":"Vintage 1920u2019s Mother Hubbard Pancake Flour Tin 5 Lb Mankato Minn ","link":"http://rover.ebay.com/rover/1/711-53200-19255-0/1?campid=5336393622&toolid=10013&customId=advertising/tins&mpre=http://www.ebay.com/itm/221988003432","meta":{"price":1999,"date":{"formatted":"2016-01-14T08:00:00.000Z","origin":"-15 hours ago"},"bids":1,"watchers":0},"src":{"original":"http://thumbs1.ebaystatic.com/m/mL2SYwraZ-momFkUPY58P0w/140.jpg","local":"2016/01/14/ntb9/t.jpg"},"images":{"original":["http://i.ebayimg.com/images/g/H2kAAOSwJkJWjbLe/s-l64.jpg","http://i.ebayimg.com/images/g/21AAAOSwa-dWjbLK/s-l64.jpg","http://i.ebayimg.com/images/g/2fcAAOSwa-dWjbK4/s-l64.jpg","http://i.ebayimg.com/images/g/EXUAAOSwJkJWjbIb/s-l64.jpg","http://i.ebayimg.com/images/g/v1oAAOSwaA5WjbKp/s-l64.jpg","http://i.ebayimg.com/images/g/GTMAAOSwX~dWjbIu/s-l64.jpg","http://i.ebayimg.com/images/g/sYwAAOSwwPhWjbI5/s-l64.jpg","http://i.ebayimg.com/images/g/tKAAAOSwL7VWjbKM/s-l64.jpg","http://i.ebayimg.com/images/g/xGUAAOSwHaBWjbJM/s-l64.jpg","http://i.ebayimg.com/images/g/DoUAAOSwLN5WjbJZ/s-l64.jpg","http://i.ebayimg.com/images/g/tTIAAOSwwPhWjbJj/s-l64.jpg","http://i.ebayimg.com/images/g/u0gAAOSwaA5WjbJr/s-l64.jpg"],"local":["2016/01/14/ntb9/i_0.jpg","2016/01/14/ntb9/i_1.jpg","2016/01/14/ntb9/i_2.jpg","2016/01/14/ntb9/i_3.jpg","2016/01/14/ntb9/i_4.jpg","2016/01/14/ntb9/i_5.jpg","2016/01/14/ntb9/i_6.jpg","2016/01/14/ntb9/i_7.jpg","2016/01/14/ntb9/i_8.jpg","2016/01/14/ntb9/i_9.jpg","2016/01/14/ntb9/i_10.jpg","2016/01/14/ntb9/i_11.jpg"]}},{"id":"ts91","title":"Vintage White Villa Grocers Tea Tin Can Hinged Lid Cincinnati Distributors","link":"http://rover.ebay.com/rover/1/711-53200-19255-0/1?campid=5336393622&toolid=10013&customId=advertising/tins&mpre=http://www.ebay.com/itm/321966177889","meta":{"price":1896,"date":{"formatted":"2016-01-14T08:00:00.000Z","origin":"-13 hours ago"},"bids":1,"watchers":2},"src":{"original":"http://thumbs2.ebaystatic.com/m/mp_-LNt663HuZxUVwMP1RbQ/140.jpg","local":"2016/01/14/ts91/t.jpg"},"images":{"original":["http://i.ebayimg.com/images/g/DcAAAOSwSdZWfEgO/s-l64.jpg","http://i.ebayimg.com/images/g/LHwAAOSwNyFWfEg4/s-l64.jpg","http://i.ebayimg.com/images/g/t6wAAOSwCQNWfEho/s-l64.jpg","http://i.ebayimg.com/images/g/SUYAAOSwYaFWfEiS/s-l64.jpg","http://i.ebayimg.com/images/g/xaQAAOSw3KFWfEjF/s-l64.jpg","http://i.ebayimg.com/images/g/~UAAAOSwHPlWfEj1/s-l64.jpg","http://i.ebayimg.com/images/g/~1YAAOSwHPlWfEkh/s-l64.jpg"],"local":["2016/01/14/ts91/i_0.jpg","2016/01/14/ts91/i_1.jpg","2016/01/14/ts91/i_2.jpg","2016/01/14/ts91/i_3.jpg","2016/01/14/ts91/i_4.jpg","2016/01/14/ts91/i_5.jpg","2016/01/14/ts91/i_6.jpg"]}},{"id":"0q94","title":"Weideman Spice Tin-2.5\"x2\"x1\",tin,cond.9,c.1940s.1.5 Oz.cleveland","link":"http://rover.ebay.com/rover/1/711-53200-19255-0/1?campid=5336393622&toolid=10013&customId=advertising/tins&mpre=http://www.ebay.com/itm/172053398122","meta":{"price":1850,"date":{"formatted":"2016-01-14T08:00:00.000Z","origin":"-18 hours ago"},"bids":5,"watchers":4},"src":{"original":"http://thumbs3.ebaystatic.com/m/mSRyb2RTH0VPLjQwRyxBJdA/140.jpg","local":"2016/01/14/0q94/t.jpg"},"images":{"original":["http://i.ebayimg.com/images/g/hLwAAOSwYIhWjYwL/s-l64.jpg","http://i.ebayimg.com/images/g/B9IAAOSwZG9WjYwS/s-l64.jpg"],"local":["2016/01/14/0q94/i_0.jpg","2016/01/14/0q94/i_1.jpg"]}},{"id":"augz","title":"Ko-we-ba Spice Tin-3.5\"x2\"x1\",tin,cond.9+,.c.1940s.2 Oz.nos&full.indianapolis","link":"http://rover.ebay.com/rover/1/711-53200-19255-0/1?campid=5336393622&toolid=10013&customId=advertising/tins&mpre=http://www.ebay.com/itm/172053327261","meta":{"price":1850,"date":{"formatted":"2016-01-14T08:00:00.000Z","origin":"-18 hours ago"},"bids":4,"watchers":3},"src":{"original":"http://thumbs2.ebaystatic.com/m/mds9rRvSGeQBOQv6Xb5NpaA/140.jpg","local":"2016/01/14/augz/t.jpg"},"images":{"original":["http://i.ebayimg.com/images/g/DKIAAOSwZG9WjYLF/s-l64.jpg","http://i.ebayimg.com/images/g/jVoAAOSwT~9WjYLK/s-l64.jpg","http://i.ebayimg.com/images/g/KpgAAOSwwPhWjYLR/s-l64.jpg"],"local":["2016/01/14/augz/i_0.jpg","2016/01/14/augz/i_1.jpg","2016/01/14/augz/i_2.jpg"]}},{"id":"jc7o","title":"Huge Lot Of 20 Coca Cola Metal Tins","link":"http://rover.ebay.com/rover/1/711-53200-19255-0/1?campid=5336393622&toolid=10013&customId=advertising/tins&mpre=http://www.ebay.com/itm/281904753286","meta":{"price":1750,"date":{"formatted":"2016-01-14T08:00:00.000Z","origin":"-4 hours ago"},"bids":8,"watchers":2},"src":{"original":"http://thumbs3.ebaystatic.com/m/mpO1SeG6xO-3QV-7z_7P3ow/140.jpg","local":"2016/01/14/jc7o/t.jpg"},"images":{"original":["http://i.ebayimg.com/images/g/UfAAAOSw1S9WezTg/s-l64.jpg","http://i.ebayimg.com/images/g/qWUAAOSwUdlWezTl/s-l64.jpg","http://i.ebayimg.com/images/g/UpMAAOSw1S9WezTr/s-l64.jpg","http://i.ebayimg.com/images/g/VeEAAOSwhkRWezTx/s-l64.jpg","http://i.ebayimg.com/images/g/vuEAAOSw~otWezT2/s-l64.jpg","http://i.ebayimg.com/images/g/Y34AAOSwZ1lWezT7/s-l64.jpg"],"local":["2016/01/14/jc7o/i_0.jpg","2016/01/14/jc7o/i_1.jpg","2016/01/14/jc7o/i_2.jpg","2016/01/14/jc7o/i_3.jpg","2016/01/14/jc7o/i_4.jpg","2016/01/14/jc7o/i_5.jpg"]}},{"id":"flxg","title":"2 Vintage Green Metal Tin Lard Pail Buckets Armour & Pierz Mn Primitive Kitchen","link":"http://rover.ebay.com/rover/1/711-53200-19255-0/1?campid=5336393622&toolid=10013&customId=advertising/tins&mpre=http://www.ebay.com/itm/161939359633","meta":{"price":1745,"date":{"formatted":"2016-01-14T08:00:00.000Z","origin":"-14 hours ago"},"bids":3,"watchers":3},"src":{"original":"http://thumbs2.ebaystatic.com/m/mL8pnr89puIeA9Y6f3X7bvw/140.jpg","local":"2016/01/14/flxg/t.jpg"},"images":{"original":["http://i.ebayimg.com/images/g/LrEAAOSwa-dWjZU5/s-l64.jpg","http://i.ebayimg.com/images/g/l7YAAOSwa-dWjY-J/s-l64.jpg","http://i.ebayimg.com/images/g/qboAAOSwGotWjZU-/s-l64.jpg","http://i.ebayimg.com/images/g/SBYAAOSwL7VWjZVF/s-l64.jpg","http://i.ebayimg.com/images/g/MMgAAOSwa-dWjZVL/s-l64.jpg","http://i.ebayimg.com/images/g/SWEAAOSwL7VWjZVR/s-l64.jpg","http://i.ebayimg.com/images/g/H4AAAOSwwPhWjZVY/s-l64.jpg","http://i.ebayimg.com/images/g/VzYAAOSwoydWjZVe/s-l64.jpg","http://i.ebayimg.com/images/g/H00AAOSwHaBWjZVl/s-l64.jpg","http://i.ebayimg.com/images/g/pAgAAOSw5dNWjZY4/s-l64.jpg","http://i.ebayimg.com/images/g/SL4AAOSwa-dWjZY-/s-l64.jpg","http://i.ebayimg.com/images/g/vjEAAOSwoydWjY8I/s-l64.jpg"],"local":["2016/01/14/flxg/i_0.jpg","2016/01/14/flxg/i_1.jpg","2016/01/14/flxg/i_2.jpg","2016/01/14/flxg/i_3.jpg","2016/01/14/flxg/i_4.jpg","2016/01/14/flxg/i_5.jpg","2016/01/14/flxg/i_6.jpg","2016/01/14/flxg/i_7.jpg","2016/01/14/flxg/i_8.jpg","2016/01/14/flxg/i_9.jpg","2016/01/14/flxg/i_10.jpg","2016/01/14/flxg/i_11.jpg"]}},{"id":"xgpr","title":"Vintage Lucky Strike Roll Cut Tobacco Pocket Tin Can Advertising Factory 2 Md","link":"http://rover.ebay.com/rover/1/711-53200-19255-0/1?campid=5336393622&toolid=10013&customId=advertising/tins&mpre=http://www.ebay.com/itm/272097161251","meta":{"price":1716,"date":{"formatted":"2016-01-14T08:00:00.000Z","origin":"-20 hours ago"},"bids":2,"watchers":6},"src":{"original":"http://thumbs4.ebaystatic.com/m/m8nNs86TLB5qmd8Od4gWC8w/140.jpg","local":"2016/01/14/xgpr/t.jpg"},"images":{"original":["http://i.ebayimg.com/images/g/U5oAAOSwHaBWjWQw/s-l64.jpg","http://i.ebayimg.com/images/g/DbAAAOSwT~9WjWQ3/s-l64.jpg","http://i.ebayimg.com/images/g/rqAAAOSwwPhWjWQs/s-l64.jpg","http://i.ebayimg.com/images/g/U1kAAOSwHaBWjWQv/s-l64.jpg","http://i.ebayimg.com/images/g/DP0AAOSwT~9WjWQy/s-l64.jpg","http://i.ebayimg.com/images/g/sDQAAOSwwPhWjWQ2/s-l64.jpg","http://i.ebayimg.com/images/g/~6wAAOSwX~dWjWQ5/s-l64.jpg","http://i.ebayimg.com/images/g/sVUAAOSwwPhWjWQ9/s-l64.jpg","http://i.ebayimg.com/images/g/VW8AAOSwL7VWjWRB/s-l64.jpg"],"local":["2016/01/14/xgpr/i_0.jpg","2016/01/14/xgpr/i_1.jpg","2016/01/14/xgpr/i_2.jpg","2016/01/14/xgpr/i_3.jpg","2016/01/14/xgpr/i_4.jpg","2016/01/14/xgpr/i_5.jpg","2016/01/14/xgpr/i_6.jpg","2016/01/14/xgpr/i_7.jpg","2016/01/14/xgpr/i_8.jpg"]}},{"id":"5qdk","title":"Folgers Spice Tin-3.5\"x2\"x1\",tin,cond.9,c.1940s.2 Oz.clean & Bright.sanfrancisc0","link":"http://rover.ebay.com/rover/1/711-53200-19255-0/1?campid=5336393622&toolid=10013&customId=advertising/tins&mpre=http://www.ebay.com/itm/191776557071","meta":{"price":1650,"date":{"formatted":"2016-01-14T08:00:00.000Z","origin":"-18 hours ago"},"bids":3,"watchers":5},"src":{"original":"http://thumbs4.ebaystatic.com/m/mKGEBAvmxAFTsOKj4l3uIIQ/140.jpg","local":"2016/01/14/5qdk/t.jpg"},"images":{"original":["http://i.ebayimg.com/images/g/P40AAOSwZG9WjYSU/s-l64.jpg","http://i.ebayimg.com/images/g/zV0AAOSwLN5WjYSZ/s-l64.jpg","http://i.ebayimg.com/images/g/lP0AAOSwaA5WjYSg/s-l64.jpg","http://i.ebayimg.com/images/g/KeIAAOSwKtlWjYSl/s-l64.jpg","http://i.ebayimg.com/images/g/CkAAAOSwGotWjYSr/s-l64.jpg","http://i.ebayimg.com/images/g/spMAAOSwoydWjYSx/s-l64.jpg"],"local":["2016/01/14/5qdk/i_0.jpg","2016/01/14/5qdk/i_1.jpg","2016/01/14/5qdk/i_2.jpg","2016/01/14/5qdk/i_3.jpg","2016/01/14/5qdk/i_4.jpg","2016/01/14/5qdk/i_5.jpg"]}},{"id":"121h","title":"Blayney Murphy's Holly Pure Lard Tin Bucket Paper Label Vintage 8 Lb Denver Co","link":"http://rover.ebay.com/rover/1/711-53200-19255-0/1?campid=5336393622&toolid=10013&customId=advertising/tins&mpre=http://www.ebay.com/itm/331748520058","meta":{"price":1600,"date":{"formatted":"2016-01-14T08:00:00.000Z","origin":"-11 hours ago"},"bids":1,"watchers":1},"src":{"original":"http://thumbs3.ebaystatic.com/m/mJ1zDqM9Nx7PWV8VgpZCYdg/140.jpg","local":"2016/01/14/121h/t.jpg"},"images":{"original":["http://i.ebayimg.com/images/g/1x0AAOSw~gRVsTaW/s-l64.jpg","http://i.ebayimg.com/images/g/JDoAAOSwu4BVsTad/s-l64.jpg","http://i.ebayimg.com/images/g/a1UAAOSwMmBVsTal/s-l64.jpg"],"local":["2016/01/14/121h/i_0.jpg","2016/01/14/121h/i_1.jpg","2016/01/14/121h/i_2.jpg"]}},{"id":"21mj","title":"Wonderful! Antique Vintage 'the 3 Little Pigs' Tin Ca. 1930","link":"http://rover.ebay.com/rover/1/711-53200-19255-0/1?campid=5336393622&toolid=10013&customId=advertising/tins&mpre=http://www.ebay.com/itm/181983629346","meta":{"price":1500,"date":{"formatted":"2016-01-14T08:00:00.000Z","origin":"-17 hours ago"},"bids":1,"watchers":1},"src":{"original":"http://thumbs3.ebaystatic.com/m/mN2Jh6-Febw0tOJKWSQOdhw/140.jpg","local":"2016/01/14/21mj/t.jpg"},"images":{"original":["http://i.ebayimg.com/images/g/TjIAAOSwZG9WjY65/s-l64.jpg","http://i.ebayimg.com/images/g/23wAAOSw5dNWjY66/s-l64.jpg","http://i.ebayimg.com/images/g/C5YAAOSwGotWjY67/s-l64.jpg","http://i.ebayimg.com/images/g/1nwAAOSwT~9WjY69/s-l64.jpg","http://i.ebayimg.com/images/g/YIgAAOSwKtlWjY6-/s-l64.jpg","http://i.ebayimg.com/images/g/te8AAOSwoydWjY7A/s-l64.jpg","http://i.ebayimg.com/images/g/DFMAAOSwGotWjY7B/s-l64.jpg","http://i.ebayimg.com/images/g/TvcAAOSwZG9WjY7C/s-l64.jpg"],"local":["2016/01/14/21mj/i_0.jpg","2016/01/14/21mj/i_1.jpg","2016/01/14/21mj/i_2.jpg","2016/01/14/21mj/i_3.jpg","2016/01/14/21mj/i_4.jpg","2016/01/14/21mj/i_5.jpg","2016/01/14/21mj/i_6.jpg","2016/01/14/21mj/i_7.jpg"]}},{"id":"lmru","title":"Vintage Mica Axle Grease Standard Oil Miniature Handled Galvanized Pail","link":"http://rover.ebay.com/rover/1/711-53200-19255-0/1?campid=5336393622&toolid=10013&customId=advertising/tins&mpre=http://www.ebay.com/itm/381514678854","meta":{"price":1499,"date":{"formatted":"2016-01-14T08:00:00.000Z","origin":"-11 hours ago"},"bids":1,"watchers":5},"src":{"original":"http://thumbs3.ebaystatic.com/m/m0BgAoAEWyd0hJNnIM-5STg/140.jpg","local":"2016/01/14/lmru/t.jpg"},"images":{"original":["http://i.ebayimg.com/images/g/P4AAAOSwL7VWkIV9/s-l64.jpg","http://i.ebayimg.com/images/g/YRoAAOSwFqJWkIV1/s-l64.jpg","http://i.ebayimg.com/images/g/FiQAAOSwT~9WkIVt/s-l64.jpg","http://i.ebayimg.com/images/g/yz8AAOSwKtlWkIVm/s-l64.jpg"],"local":["2016/01/14/lmru/i_0.jpg","2016/01/14/lmru/i_1.jpg","2016/01/14/lmru/i_2.jpg","2016/01/14/lmru/i_3.jpg"]}},{"id":"9zvr","title":"Antique Butter Nut Coffee Tin Litho 1lb Keywind Can Paxton Gallagher Omaha Ne","link":"http://rover.ebay.com/rover/1/711-53200-19255-0/1?campid=5336393622&toolid=10013&customId=advertising/tins&mpre=http://www.ebay.com/itm/331748450164","meta":{"price":1499,"date":{"formatted":"2016-01-14T08:00:00.000Z","origin":"-14 hours ago"},"bids":2,"watchers":0},"src":{"original":"http://thumbs1.ebaystatic.com/m/mpdH2JjmzxQP0W_lhoV_1bw/140.jpg","local":"2016/01/14/9zvr/t.jpg"},"images":{"original":["http://i.ebayimg.com/images/g/W7sAAOSwKtlWjcRG/s-l64.jpg","http://i.ebayimg.com/images/g/XAQAAOSwLN5WjcRc/s-l64.jpg","http://i.ebayimg.com/images/g/WTEAAOSwJkJWjcR6/s-l64.jpg","http://i.ebayimg.com/images/g/WygAAOSwJkJWjcSR/s-l64.jpg","http://i.ebayimg.com/images/g/NOMAAOSwa-dWjcSo/s-l64.jpg","http://i.ebayimg.com/images/g/hVUAAOSwT~9WjcS~/s-l64.jpg"],"local":["2016/01/14/9zvr/i_0.jpg","2016/01/14/9zvr/i_1.jpg","2016/01/14/9zvr/i_2.jpg","2016/01/14/9zvr/i_3.jpg","2016/01/14/9zvr/i_4.jpg","2016/01/14/9zvr/i_5.jpg"]}},{"id":"js8g","title":"Vintage Rawleigh's Ideal Oil Tin-all Purpose Oil-funnel Cap","link":"http://rover.ebay.com/rover/1/711-53200-19255-0/1?campid=5336393622&toolid=10013&customId=advertising/tins&mpre=http://www.ebay.com/itm/351622239701","meta":{"price":1495,"date":{"formatted":"2016-01-14T08:00:00.000Z","origin":"-13 hours ago"},"bids":1,"watchers":1},"src":{"original":"http://thumbs2.ebaystatic.com/m/mjNC6zmPBIrWP1K4LTINXMw/140.jpg","local":"2016/01/14/js8g/t.jpg"},"images":{"original":["http://i.ebayimg.com/images/g/BXsAAOSwJkJWjTt1/s-l64.jpg","http://i.ebayimg.com/images/g/LWEAAOSwKtlWjTt5/s-l64.jpg","http://i.ebayimg.com/images/g/LpUAAOSwwPhWjTt-/s-l64.jpg","http://i.ebayimg.com/images/g/LsQAAOSwKtlWjTuE/s-l64.jpg"],"local":["2016/01/14/js8g/i_0.jpg","2016/01/14/js8g/i_1.jpg","2016/01/14/js8g/i_2.jpg","2016/01/14/js8g/i_3.jpg"]}},{"id":"s0b4","title":" Vintage Aspirin Tin St Joseph Old Orange & Zebra Stripe Design Empty","link":"http://rover.ebay.com/rover/1/711-53200-19255-0/1?campid=5336393622&toolid=10013&customId=advertising/tins&mpre=http://www.ebay.com/itm/262232175321","meta":{"price":1373,"date":{"formatted":"2016-01-14T08:00:00.000Z","origin":"-16 mins ago"},"bids":5,"watchers":2},"src":{"original":"http://thumbs2.ebaystatic.com/m/mDoSzCUoKWeuLcGYY95-nlQ/140.jpg","local":"2016/01/14/s0b4/t.jpg"},"images":{"original":["http://i.ebayimg.com/images/g/sZgAAOSw3KFWcNH7/s-l64.jpg","http://i.ebayimg.com/images/g/g~QAAOSwJcZWcNIG/s-l64.jpg"],"local":["2016/01/14/s0b4/i_0.jpg","2016/01/14/s0b4/i_1.jpg"]}},{"id":"t41l","title":"Vintage O'connor's Vacuumed Packed Coffee Tin Can","link":"http://rover.ebay.com/rover/1/711-53200-19255-0/1?campid=5336393622&toolid=10013&customId=advertising/tins&mpre=http://www.ebay.com/itm/281902804600","meta":{"price":1300,"date":{"formatted":"2016-01-14T08:00:00.000Z","origin":"-18 hours ago"},"bids":1,"watchers":2},"src":{"original":"http://thumbs1.ebaystatic.com/m/mMHED7FdnKwuc2CwV0aHE_Q/140.jpg","local":"2016/01/14/t41l/t.jpg"},"images":{"original":["http://i.ebayimg.com/images/g/j9sAAOSw8-tWU7ap/s-l64.jpg","http://i.ebayimg.com/images/g/kw4AAOSwwE5WU7au/s-l64.jpg","http://i.ebayimg.com/images/g/-jUAAOSwf-VWU7a4/s-l64.jpg","http://i.ebayimg.com/images/g/iQsAAOSw7FRWU7ar/s-l64.jpg","http://i.ebayimg.com/images/g/37oAAOSwxN5WU7av/s-l64.jpg","http://i.ebayimg.com/images/g/kI0AAOSw8-tWU7az/s-l64.jpg"],"local":["2016/01/14/t41l/i_0.jpg","2016/01/14/t41l/i_1.jpg","2016/01/14/t41l/i_2.jpg","2016/01/14/t41l/i_3.jpg","2016/01/14/t41l/i_4.jpg","2016/01/14/t41l/i_5.jpg"]}},{"id":"m8as","title":"Vtg Ritz Crackers, Saltine Crackers And Barnums Animal Cracker Decor Kitchen Tin","link":"http://rover.ebay.com/rover/1/711-53200-19255-0/1?campid=5336393622&toolid=10013&customId=advertising/tins&mpre=http://www.ebay.com/itm/161939539563","meta":{"price":1299,"date":{"formatted":"2016-01-14T08:00:00.000Z","origin":"-12 hours ago"},"bids":1,"watchers":1},"src":{"original":"http://thumbs4.ebaystatic.com/m/mAcPk9QktHatNWKirwSF55w/140.jpg","local":"2016/01/14/m8as/t.jpg"},"images":{"original":["http://i.ebayimg.com/images/g/7ucAAOSwLN5WjdpA/s-l300.jpg"],"local":["2016/01/14/m8as/i_0.jpg"]}},{"id":"n7yc","title":"Prince Albert Tobacco Tin Match Safe","link":"http://rover.ebay.com/rover/1/711-53200-19255-0/1?campid=5336393622&toolid=10013&customId=advertising/tins&mpre=http://www.ebay.com/itm/111867987158","meta":{"price":1266,"date":{"formatted":"2016-01-14T08:00:00.000Z","origin":"-14 hours ago"},"bids":9,"watchers":11},"src":{"original":"http://thumbs3.ebaystatic.com/m/mZcA7CcjjmHBkRC0X8jC5gw/140.jpg","local":"2016/01/14/n7yc/t.jpg"},"images":{"original":["http://i.ebayimg.com/images/g/rV0AAOSwGotWjbr0/s-l64.jpg","http://i.ebayimg.com/images/g/fmcAAOSwoydWjbr-/s-l64.jpg","http://i.ebayimg.com/images/g/zvoAAOSwX~dWjbsH/s-l64.jpg"],"local":["2016/01/14/n7yc/i_0.jpg","2016/01/14/n7yc/i_1.jpg","2016/01/14/n7yc/i_2.jpg"]}},{"id":"g2tw","title":"Arco Spice Tin-2.25\"x1.75\"x1.25\",tinw.cdbd,cond.8,c.1940s.1 Oz.litchfield. Il","link":"http://rover.ebay.com/rover/1/711-53200-19255-0/1?campid=5336393622&toolid=10013&customId=advertising/tins&mpre=http://www.ebay.com/itm/191776581296","meta":{"price":1250,"date":{"formatted":"2016-01-14T08:00:00.000Z","origin":"-17 hours ago"},"bids":4,"watchers":0},"src":{"original":"http://thumbs1.ebaystatic.com/m/mC9d39cakBpL1ZPNWnw1epA/140.jpg","local":"2016/01/14/g2tw/t.jpg"},"images":{"original":["http://i.ebayimg.com/images/g/znAAAOSwoydWjY-W/s-l64.jpg","http://i.ebayimg.com/images/g/f4MAAOSwKtlWjY-b/s-l64.jpg"],"local":["2016/01/14/g2tw/i_0.jpg","2016/01/14/g2tw/i_1.jpg"]}},{"id":"35hl","title":"Hawley & Hoops Antique Sample Size Breakfast Cocoa Tin","link":"http://rover.ebay.com/rover/1/711-53200-19255-0/1?campid=5336393622&toolid=10013&customId=advertising/tins&mpre=http://www.ebay.com/itm/221988023578","meta":{"price":1050,"date":{"formatted":"2016-01-14T08:00:00.000Z","origin":"-14 hours ago"},"bids":2,"watchers":0},"src":{"original":"http://thumbs3.ebaystatic.com/m/mTh1T3KBaLTyOMbdKCosM8w/140.jpg","local":"2016/01/14/35hl/t.jpg"},"images":{"original":["http://i.ebayimg.com/images/g/PZ0AAOSwLVZVxlEN/s-l64.jpg","http://i.ebayimg.com/images/g/liMAAOSw9N1VxlD6/s-l64.jpg","http://i.ebayimg.com/images/g/PN4AAOSwLVZVxlEF/s-l64.jpg","http://i.ebayimg.com/images/g/kMkAAOSwd0BVxlEV/s-l64.jpg","http://i.ebayimg.com/images/g/07IAAOSwu4BVxlEe/s-l64.jpg","http://i.ebayimg.com/images/g/kycAAOSwjVVVxlEm/s-l64.jpg","http://i.ebayimg.com/images/g/nAUAAOSw9N1VxlEw/s-l64.jpg","http://i.ebayimg.com/images/g/mk8AAOSwgQ9VxlE5/s-l64.jpg"],"local":["2016/01/14/35hl/i_0.jpg","2016/01/14/35hl/i_1.jpg","2016/01/14/35hl/i_2.jpg","2016/01/14/35hl/i_3.jpg","2016/01/14/35hl/i_4.jpg","2016/01/14/35hl/i_5.jpg","2016/01/14/35hl/i_6.jpg","2016/01/14/35hl/i_7.jpg"]}},{"id":"ma4i","title":"Watkins Spice Tin-4.25\"x2\"x1\",tin,cond.9,c.1940s.8 Oz.winona,mn","link":"http://rover.ebay.com/rover/1/711-53200-19255-0/1?campid=5336393622&toolid=10013&customId=advertising/tins&mpre=http://www.ebay.com/itm/191776576337","meta":{"price":999,"date":{"formatted":"2016-01-14T08:00:00.000Z","origin":"-18 hours ago"},"bids":1,"watchers":2},"src":{"original":"http://thumbs2.ebaystatic.com/m/mvoPIc7XgVNqWMUIsuNfy3Q/140.jpg","local":"2016/01/14/ma4i/t.jpg"},"images":{"original":["http://i.ebayimg.com/images/g/u9IAAOSw5dNWjY18/s-l64.jpg","http://i.ebayimg.com/images/g/P0kAAOSwHaBWjY1~/s-l64.jpg","http://i.ebayimg.com/images/g/ZcYAAOSwFqJWjY2G/s-l64.jpg"],"local":["2016/01/14/ma4i/i_0.jpg","2016/01/14/ma4i/i_1.jpg","2016/01/14/ma4i/i_2.jpg"]}},{"id":"60r3","title":"J.g Dills Best Cut Plug Tobacco Tin Vintage Advertising Larger Tin","link":"http://rover.ebay.com/rover/1/711-53200-19255-0/1?campid=5336393622&toolid=10013&customId=advertising/tins&mpre=http://www.ebay.com/itm/252240626949","meta":{"price":999,"date":{"formatted":"2016-01-14T08:00:00.000Z","origin":"-14 hours ago"},"bids":1,"watchers":2},"src":{"original":"http://thumbs2.ebaystatic.com/m/m0QIxXM_1CfGG_hINS-bNCA/140.jpg","local":"2016/01/14/60r3/t.jpg"},"images":{"original":["http://i.ebayimg.com/images/g/S9cAAOSwKtlWhH5k/s-l64.jpg","http://i.ebayimg.com/images/g/W5wAAOSwJkJWhH59/s-l64.jpg","http://i.ebayimg.com/images/g/osMAAOSwaA5WhH6U/s-l64.jpg","http://i.ebayimg.com/images/g/XrAAAOSwJkJWhH6v/s-l64.jpg","http://i.ebayimg.com/images/g/vnwAAOSw5dNWhH7O/s-l64.jpg","http://i.ebayimg.com/images/g/YaQAAOSwJkJWhH7f/s-l64.jpg","http://i.ebayimg.com/images/g/GWYAAOSwL7VWhH71/s-l64.jpg"],"local":["2016/01/14/60r3/i_0.jpg","2016/01/14/60r3/i_1.jpg","2016/01/14/60r3/i_2.jpg","2016/01/14/60r3/i_3.jpg","2016/01/14/60r3/i_4.jpg","2016/01/14/60r3/i_5.jpg","2016/01/14/60r3/i_6.jpg"]}},{"id":"5g7b","title":"Lot Of 5 Edgeworth Extra High Grade Sliced Pipe Tobacco Tin Richmond Usa","link":"http://rover.ebay.com/rover/1/711-53200-19255-0/1?campid=5336393622&toolid=10013&customId=advertising/tins&mpre=http://www.ebay.com/itm/311519784813","meta":{"price":999,"date":{"formatted":"2016-01-14T08:00:00.000Z","origin":"-13 hours ago"},"bids":1,"watchers":2},"src":{"original":"http://thumbs2.ebaystatic.com/m/mKpqQNBd6cCG1Z_WPHZz0jg/140.jpg","local":"2016/01/14/5g7b/t.jpg"},"images":{"original":["http://i.ebayimg.com/images/g/ayQAAOSwoydWjcgv/s-l64.jpg","http://i.ebayimg.com/images/g/nToAAOSwJkJWjcgy/s-l64.jpg","http://i.ebayimg.com/images/g/rvQAAOSwKtlWjcg2/s-l64.jpg"],"local":["2016/01/14/5g7b/i_0.jpg","2016/01/14/5g7b/i_1.jpg","2016/01/14/5g7b/i_2.jpg"]}},{"id":"kxmk","title":"Scarce Vintage Bigelow Constant Comment Tea Tin-24 Ct-partially Full Advertising","link":"http://rover.ebay.com/rover/1/711-53200-19255-0/1?campid=5336393622&toolid=10013&customId=advertising/tins&mpre=http://www.ebay.com/itm/131692084248","meta":{"price":999,"date":{"formatted":"2016-01-14T08:00:00.000Z","origin":"-14 hours ago"},"bids":1,"watchers":0},"src":{"original":"http://thumbs1.ebaystatic.com/m/m9IJ3BYAEWEuTqjvtT4oV-g/140.jpg","local":"2016/01/14/kxmk/t.jpg"},"images":{"original":["http://i.ebayimg.com/images/g/ebEAAOSwa-dWica0/s-l300.jpg"],"local":["2016/01/14/kxmk/i_0.jpg"]}},{"id":"xpxx","title":"Serv-us Spice Tin-4\"x.5\",round Tin,cond.9,c.1940s.2 Oz.new York.clean & Bright.","link":"http://rover.ebay.com/rover/1/711-53200-19255-0/1?campid=5336393622&toolid=10013&customId=advertising/tins&mpre=http://www.ebay.com/itm/191776584776","meta":{"price":999,"date":{"formatted":"2016-01-14T08:00:00.000Z","origin":"-17 hours ago"},"bids":1,"watchers":0},"src":{"original":"http://thumbs1.ebaystatic.com/m/m_aIIwBoNA3P4UDR-9pp96A/140.jpg","local":"2016/01/14/xpxx/t.jpg"},"images":{"original":["http://i.ebayimg.com/images/g/t-YAAOSwKtlWjZGo/s-l64.jpg","http://i.ebayimg.com/images/g/QewAAOSwJkJWjZGt/s-l64.jpg","http://i.ebayimg.com/images/g/IegAAOSwX~dWjZGz/s-l64.jpg","http://i.ebayimg.com/images/g/0PkAAOSwa-dWjZG5/s-l64.jpg","http://i.ebayimg.com/images/g/HDQAAOSwYIhWjZG-/s-l64.jpg"],"local":["2016/01/14/xpxx/i_0.jpg","2016/01/14/xpxx/i_1.jpg","2016/01/14/xpxx/i_2.jpg","2016/01/14/xpxx/i_3.jpg","2016/01/14/xpxx/i_4.jpg"]}},{"id":"me52","title":"Antique Vintage Spice Tins Durkee's Lot Of 3 ","link":"http://rover.ebay.com/rover/1/711-53200-19255-0/1?campid=5336393622&toolid=10013&customId=advertising/tins&mpre=http://www.ebay.com/itm/172053113158","meta":{"price":925,"date":{"formatted":"2016-01-14T08:00:00.000Z","origin":"-21 hours ago"},"bids":2,"watchers":2},"src":{"original":"http://thumbs3.ebaystatic.com/m/mglxUQc4ZiuoL4hbAKgry-w/140.jpg","local":"2016/01/14/me52/t.jpg"},"images":{"original":["http://i.ebayimg.com/images/g/cNsAAOSweuxWT3pd/s-l64.jpg","http://i.ebayimg.com/images/g/FrEAAOSwlV9WT3ps/s-l64.jpg","http://i.ebayimg.com/images/g/v30AAOSwcdBWT3p7/s-l64.jpg","http://i.ebayimg.com/images/g/GWoAAOSwFGNWT3qL/s-l64.jpg","http://i.ebayimg.com/images/g/6p8AAOSwnGJWT3qa/s-l64.jpg","http://i.ebayimg.com/images/g/HwgAAOSwFGNWT3qs/s-l64.jpg"],"local":["2016/01/14/me52/i_0.jpg","2016/01/14/me52/i_1.jpg","2016/01/14/me52/i_2.jpg","2016/01/14/me52/i_3.jpg","2016/01/14/me52/i_4.jpg","2016/01/14/me52/i_5.jpg"]}},{"id":"fwzz","title":"Ottoman . Antique Turkish \" Monopole \" Cigarette Tin . 20 Cigarettes. Empty.","link":"http://rover.ebay.com/rover/1/711-53200-19255-0/1?campid=5336393622&toolid=10013&customId=advertising/tins&mpre=http://www.ebay.com/itm/172055450948","meta":{"price":650,"date":{"formatted":"2016-01-14T08:00:00.000Z","origin":"-22 hours ago"},"bids":2,"watchers":3},"src":{"original":"http://thumbs1.ebaystatic.com/m/m6rI6KrwZ2BSMC_bwpqDGEg/140.jpg","local":"2016/01/14/fwzz/t.jpg"},"images":{"original":["http://i.ebayimg.com/images/g/gyUAAOSwL7VWj-5Q/s-l64.jpg","http://i.ebayimg.com/images/g/rCYAAOSwZG9Wj-5s/s-l64.jpg","http://i.ebayimg.com/images/g/HZIAAOSwHaBWj-50/s-l64.jpg"],"local":["2016/01/14/fwzz/i_0.jpg","2016/01/14/fwzz/i_1.jpg","2016/01/14/fwzz/i_2.jpg"]}},{"id":"l640","title":"Rare Early 20th Century Zig Zag Rolling Papers Tobacco Dispenser Tin Sign 5cent","link":"http://rover.ebay.com/rover/1/711-53200-19255-0/1?campid=5336393622&toolid=10013&customId=advertising/tins&mpre=http://www.ebay.com/itm/281903004026","meta":{"price":500,"date":{"formatted":"2016-01-14T08:00:00.000Z","origin":"-12 hours ago"},"bids":0,"watchers":9},"src":{"original":"http://thumbs3.ebaystatic.com/m/mFhyiMu27McxizCqExJ7qjw/140.jpg","local":"2016/01/14/l640/t.jpg"},"images":{"original":["http://i.ebayimg.com/images/g/qjQAAOSwL7VWjd12/s-l64.jpg","http://i.ebayimg.com/images/g/Nf8AAOSwwPhWjdRD/s-l64.jpg","http://i.ebayimg.com/images/g/kToAAOSwHnFVtstT/s-l64.jpg","http://i.ebayimg.com/images/g/k5kAAOSwHnFVtstp/s-l64.jpg","http://i.ebayimg.com/images/g/kjIAAOSwHnFVtstc/s-l64.jpg","http://i.ebayimg.com/images/g/z5cAAOSwDNdVtstx/s-l64.jpg","http://i.ebayimg.com/images/g/KVgAAOSwgQ9Vtst3/s-l64.jpg","http://i.ebayimg.com/images/g/034AAOSw9N1VtsuH/s-l64.jpg"],"local":["2016/01/14/l640/i_0.jpg","2016/01/14/l640/i_1.jpg","2016/01/14/l640/i_2.jpg","2016/01/14/l640/i_3.jpg","2016/01/14/l640/i_4.jpg","2016/01/14/l640/i_5.jpg","2016/01/14/l640/i_6.jpg","2016/01/14/l640/i_7.jpg"]}},{"id":"z60r","title":"American Spirit 20th Anniversary Tin - Yellow - Empty","link":"http://rover.ebay.com/rover/1/711-53200-19255-0/1?campid=5336393622&toolid=10013&customId=advertising/tins&mpre=http://www.ebay.com/itm/201498299867","meta":{"price":500,"date":{"formatted":"2016-01-14T08:00:00.000Z","origin":"-14 hours ago"},"bids":1,"watchers":0},"src":{"original":"http://thumbs4.ebaystatic.com/m/m8WioQNRSPLj8bVBjqZO-Yg/140.jpg","local":"2016/01/14/z60r/t.jpg"},"images":{"original":["http://i.ebayimg.com/images/g/e6QAAOSwI-BWIxJc/s-l64.jpg","http://i.ebayimg.com/images/g/zPwAAOSw5VFWIxJh/s-l64.jpg","http://i.ebayimg.com/images/g/28wAAOSwo6lWIxJk/s-l64.jpg","http://i.ebayimg.com/images/g/Cs4AAOSwT5tWIxJq/s-l64.jpg","http://i.ebayimg.com/images/g/HCYAAOSwo0JWIxJu/s-l64.jpg","http://i.ebayimg.com/images/g/3LMAAOSwo6lWIxJ0/s-l64.jpg"],"local":["2016/01/14/z60r/i_0.jpg","2016/01/14/z60r/i_1.jpg","2016/01/14/z60r/i_2.jpg","2016/01/14/z60r/i_3.jpg","2016/01/14/z60r/i_4.jpg","2016/01/14/z60r/i_5.jpg"]}},{"id":"m5ds","title":"Vintage Van Rossem's Plakjes Pipe Tobacco Tin (troost Slices)","link":"http://rover.ebay.com/rover/1/711-53200-19255-0/1?campid=5336393622&toolid=10013&customId=advertising/tins&mpre=http://www.ebay.com/itm/111867710315","meta":{"price":425,"date":{"formatted":"2016-01-14T08:00:00.000Z","origin":"-15 hours ago"},"bids":9,"watchers":2},"src":{"original":"http://thumbs4.ebaystatic.com/m/mL-GVKDnL2RwXfYX8wPs0rQ/140.jpg","local":"2016/01/14/m5ds/t.jpg"},"images":{"original":["http://i.ebayimg.com/images/g/mykAAOSwwPhWjbEJ/s-l64.jpg","http://i.ebayimg.com/images/g/nKkAAOSwwPhWjbEd/s-l64.jpg","http://i.ebayimg.com/images/g/sBUAAOSwHaBWjbFA/s-l64.jpg"],"local":["2016/01/14/m5ds/i_0.jpg","2016/01/14/m5ds/i_1.jpg","2016/01/14/m5ds/i_2.jpg"]}},{"id":"0d7p","title":"M&m's Flip Top Canister Tin 2011 - New No Candy Melts In Your Mouth Not Hands","link":"http://rover.ebay.com/rover/1/711-53200-19255-0/1?campid=5336393622&toolid=10013&customId=advertising/tins&mpre=http://www.ebay.com/itm/331750042354","meta":{"price":425,"date":{"formatted":"2016-01-14T08:00:00.000Z","origin":"-12 hours ago"},"bids":3,"watchers":1},"src":{"original":"http://thumbs3.ebaystatic.com/m/m0b3Z97wftto4iq7huAatIg/140.jpg","local":"2016/01/14/0d7p/t.jpg"},"images":{"original":["http://i.ebayimg.com/images/g/LiwAAOSwFqJWkIJX/s-l64.jpg","http://i.ebayimg.com/images/g/-KsAAOSwa-dWkIJc/s-l64.jpg","http://i.ebayimg.com/images/g/454AAOSwT~9WkIJj/s-l64.jpg","http://i.ebayimg.com/images/g/t7wAAOSwwPhWkIJp/s-l64.jpg","http://i.ebayimg.com/images/g/HmQAAOSw5dNWkIJv/s-l64.jpg","http://i.ebayimg.com/images/g/WAwAAOSwaA5WkIJ0/s-l64.jpg"],"local":["2016/01/14/0d7p/i_0.jpg","2016/01/14/0d7p/i_1.jpg","2016/01/14/0d7p/i_2.jpg","2016/01/14/0d7p/i_3.jpg","2016/01/14/0d7p/i_4.jpg","2016/01/14/0d7p/i_5.jpg"]}},{"id":"nhph","title":"Tobacco Tin St Ledger Sliced Plug Imperial Tobacco Company Of Canada","link":"http://rover.ebay.com/rover/1/711-53200-19255-0/1?campid=5336393622&toolid=10013&customId=advertising/tins&mpre=http://www.ebay.com/itm/221988324256","meta":{"price":325,"date":{"formatted":"2016-01-14T08:00:00.000Z","origin":"-2 hours ago"},"bids":2,"watchers":0},"src":{"original":"http://thumbs1.ebaystatic.com/m/mUp8PhLh3Y11x7V6VEnSdNA/140.jpg","local":"2016/01/14/nhph/t.jpg"},"images":{"original":["http://i.ebayimg.com/images/g/xhkAAOSwoydWjl~w/s-l64.jpg","http://i.ebayimg.com/images/g/CVoAAOSwwPhWjl~2/s-l64.jpg","http://i.ebayimg.com/images/g/xVUAAOSwoydWjl~o/s-l64.jpg","http://i.ebayimg.com/images/g/FkwAAOSwL7VWjmAA/s-l64.jpg","http://i.ebayimg.com/images/g/Pk4AAOSwT~9WjmU7/s-l64.jpg"],"local":["2016/01/14/nhph/i_0.jpg","2016/01/14/nhph/i_1.jpg","2016/01/14/nhph/i_2.jpg","2016/01/14/nhph/i_3.jpg","2016/01/14/nhph/i_4.jpg"]}},{"id":"iesr","title":"Vintage Rare Hj Reynold Tobacco Smokin' Joe's Racing Tin 1994","link":"http://rover.ebay.com/rover/1/711-53200-19255-0/1?campid=5336393622&toolid=10013&customId=advertising/tins&mpre=http://www.ebay.com/itm/321970645774","meta":{"price":99,"date":{"formatted":"2016-01-14T08:00:00.000Z","origin":"-17 hours ago"},"bids":1,"watchers":2},"src":{"original":"http://thumbs3.ebaystatic.com/m/myYKX5-_fODCCe8HuCRvbrg/140.jpg","local":"2016/01/14/iesr/t.jpg"},"images":{"original":["http://i.ebayimg.com/images/g/CUMAAOSwirZTuXx1/s-l64.jpg","http://i.ebayimg.com/images/g/Qq8AAOSw-dBTuXx4/s-l64.jpg"],"local":["2016/01/14/iesr/i_0.jpg","2016/01/14/iesr/i_1.jpg"]}}]