[{"id":"3dyz","title":"We-no-nah Leather Harness Oil Lithograph Tin Dr. Koch Veg. Tea Co. Indian 1 Gal","link":"http://rover.ebay.com/rover/1/711-53200-19255-0/1?campid=5336393622&toolid=10013&customId=advertising/tins&mpre=http://www.ebay.com/itm/262198800433","meta":{"price":13141,"date":{"formatted":"2015-12-26T08:00:00.000Z","origin":"-17 hours ago"},"bids":4,"watchers":13},"src":{"original":"http://thumbs2.ebaystatic.com/m/mPDFiGJ9nYIiMEhZ5jjXyvQ/140.jpg","local":"2015/12/26/3dyz/t.jpg"},"images":{"original":["http://i.ebayimg.com/images/g/7pkAAOSwYHxWLCMf/s-l300.jpg"],"local":["2015/12/26/3dyz/i_0.jpg"]}},{"id":"fhwe","title":"Midwest Spice Tin","link":"http://rover.ebay.com/rover/1/711-53200-19255-0/1?campid=5336393622&toolid=10013&customId=advertising/tins&mpre=http://www.ebay.com/itm/272081617140","meta":{"price":10359,"date":{"formatted":"2015-12-26T08:00:00.000Z","origin":"-14 hours ago"},"bids":19,"watchers":14},"src":{"original":"http://thumbs1.ebaystatic.com/m/mJPn5V5qRoLHmVOdRrgapxw/140.jpg","local":"2015/12/26/fhwe/t.jpg"},"images":{"original":["http://i.ebayimg.com/images/g/gKYAAOSw3KFWdLKp/s-l64.jpg","http://i.ebayimg.com/images/g/K5oAAOSwSHZWdLK1/s-l64.jpg","http://i.ebayimg.com/images/g/at0AAOSwYaFWdLLB/s-l64.jpg","http://i.ebayimg.com/images/g/YQkAAOSwo3pWdLLR/s-l64.jpg","http://i.ebayimg.com/images/g/bMoAAOSwYaFWdLLd/s-l64.jpg","http://i.ebayimg.com/images/g/mGsAAOSw5IJWdLLp/s-l64.jpg"],"local":["2015/12/26/fhwe/i_0.jpg","2015/12/26/fhwe/i_1.jpg","2015/12/26/fhwe/i_2.jpg","2015/12/26/fhwe/i_3.jpg","2015/12/26/fhwe/i_4.jpg","2015/12/26/fhwe/i_5.jpg"]}},{"id":"s8wl","title":"3 Vintage Small Tins 1933 Schilling Baking Powder, Mayfair Tea & Mellomints","link":"http://rover.ebay.com/rover/1/711-53200-19255-0/1?campid=5336393622&toolid=10013&customId=advertising/tins&mpre=http://www.ebay.com/itm/391345406250","meta":{"price":6000,"date":{"formatted":"2015-12-26T08:00:00.000Z","origin":"-17 hours ago"},"bids":16,"watchers":3},"src":{"original":"http://thumbs3.ebaystatic.com/m/mUXyUBoAySMYTsCaYol220g/140.jpg","local":"2015/12/26/s8wl/t.jpg"},"images":{"original":["http://i.ebayimg.com/images/g/wjAAAOSwHPlWdIup/s-l64.jpg","http://i.ebayimg.com/images/g/uwIAAOSwSHZWdIuw/s-l64.jpg","http://i.ebayimg.com/images/g/EMAAAOSw~otWdIu5/s-l64.jpg","http://i.ebayimg.com/images/g/floAAOSwCQNWdIvC/s-l64.jpg","http://i.ebayimg.com/images/g/xGQAAOSwHPlWdIvJ/s-l64.jpg","http://i.ebayimg.com/images/g/GewAAOSw5IJWdIvS/s-l64.jpg","http://i.ebayimg.com/images/g/AMkAAOSwZ1lWdIva/s-l64.jpg","http://i.ebayimg.com/images/g/gEYAAOSwCQNWdIvh/s-l64.jpg","http://i.ebayimg.com/images/g/37oAAOSwk1JWdIvp/s-l64.jpg","http://i.ebayimg.com/images/g/~7UAAOSwYaFWdIvw/s-l64.jpg","http://i.ebayimg.com/images/g/FKwAAOSw~otWdIv5/s-l64.jpg","http://i.ebayimg.com/images/g/VXkAAOSwNyFWdIwA/s-l64.jpg"],"local":["2015/12/26/s8wl/i_0.jpg","2015/12/26/s8wl/i_1.jpg","2015/12/26/s8wl/i_2.jpg","2015/12/26/s8wl/i_3.jpg","2015/12/26/s8wl/i_4.jpg","2015/12/26/s8wl/i_5.jpg","2015/12/26/s8wl/i_6.jpg","2015/12/26/s8wl/i_7.jpg","2015/12/26/s8wl/i_8.jpg","2015/12/26/s8wl/i_9.jpg","2015/12/26/s8wl/i_10.jpg","2015/12/26/s8wl/i_11.jpg"]}},{"id":"ou75","title":"Pair Of Premium Saltine Cracker Tins, 1969 And 1978, Vintage Decor, Nabisco Tins","link":"http://rover.ebay.com/rover/1/711-53200-19255-0/1?campid=5336393622&toolid=10013&customId=advertising/tins&mpre=http://www.ebay.com/itm/121843915603","meta":{"price":6000,"date":{"formatted":"2015-12-26T08:00:00.000Z","origin":"-13 hours ago"},"bids":33,"watchers":2},"src":{"original":"http://thumbs4.ebaystatic.com/m/mi3Kj_3Ta0MicIji57QJAuA/140.jpg","local":"2015/12/26/ou75/t.jpg"},"images":{"original":["http://i.ebayimg.com/images/g/Dv0AAOSwZ1lWdMjL/s-l64.jpg","http://i.ebayimg.com/images/g/TXsAAOSwhkRWdMjW/s-l64.jpg","http://i.ebayimg.com/images/g/oxIAAOSwo3pWdMjb/s-l64.jpg","http://i.ebayimg.com/images/g/TgIAAOSwhkRWdMjf/s-l64.jpg","http://i.ebayimg.com/images/g/TuEAAOSw1S9WdMjh/s-l64.jpg","http://i.ebayimg.com/images/g/X-8AAOSwJcZWdMjj/s-l64.jpg","http://i.ebayimg.com/images/g/~tcAAOSwCQNWdMjl/s-l64.jpg"],"local":["2015/12/26/ou75/i_0.jpg","2015/12/26/ou75/i_1.jpg","2015/12/26/ou75/i_2.jpg","2015/12/26/ou75/i_3.jpg","2015/12/26/ou75/i_4.jpg","2015/12/26/ou75/i_5.jpg","2015/12/26/ou75/i_6.jpg"]}},{"id":"n5od","title":"Vintage Model Tobacco Tin ","link":"http://rover.ebay.com/rover/1/711-53200-19255-0/1?campid=5336393622&toolid=10013&customId=advertising/tins&mpre=http://www.ebay.com/itm/281889504498","meta":{"price":5350,"date":{"formatted":"2015-12-26T08:00:00.000Z","origin":"-11 hours ago"},"bids":9,"watchers":9},"src":{"original":"http://thumbs3.ebaystatic.com/m/mUSMBNlhq9O5vy6xD_SopJw/140.jpg","local":"2015/12/26/n5od/t.jpg"},"images":{"original":["http://i.ebayimg.com/images/g/QlUAAOSwUdlWdOPd/s-l64.jpg","http://i.ebayimg.com/images/g/PgoAAOSw5IJWdOPh/s-l64.jpg"],"local":["2015/12/26/n5od/i_0.jpg","2015/12/26/n5od/i_1.jpg"]}},{"id":"if5c","title":"Vtg Late 1920u2019s Wallace Pencil Company Spirit Of St Louis Metal Pen-pencil Case","link":"http://rover.ebay.com/rover/1/711-53200-19255-0/1?campid=5336393622&toolid=10013&customId=advertising/tins&mpre=http://www.ebay.com/itm/272081554115","meta":{"price":4999,"date":{"formatted":"2015-12-26T08:00:00.000Z","origin":"-17 hours ago"},"bids":2,"watchers":2},"src":{"original":"http://thumbs4.ebaystatic.com/m/mmuPOOYg9YK52l50RZmG8-w/140.jpg","local":"2015/12/26/if5c/t.jpg"},"images":{"original":["http://i.ebayimg.com/images/g/TIoAAOSwnipWadOX/s-l64.jpg","http://i.ebayimg.com/images/g/8CYAAOSwf-VWadO4/s-l64.jpg","http://i.ebayimg.com/images/g/OaIAAOSwv-NWadPe/s-l64.jpg"],"local":["2015/12/26/if5c/i_0.jpg","2015/12/26/if5c/i_1.jpg","2015/12/26/if5c/i_2.jpg"]}},{"id":"gpmt","title":"11 Vintage Tobacco Tins","link":"http://rover.ebay.com/rover/1/711-53200-19255-0/1?campid=5336393622&toolid=10013&customId=advertising/tins&mpre=http://www.ebay.com/itm/331736198909","meta":{"price":2999,"date":{"formatted":"2015-12-26T08:00:00.000Z","origin":"-15 hours ago"},"bids":1,"watchers":4},"src":{"original":"http://thumbs2.ebaystatic.com/m/mvQJQiHaaSPetiktmO7algA/140.jpg","local":"2015/12/26/gpmt/t.jpg"},"images":{"original":["http://i.ebayimg.com/images/g/7rkAAOSwwE5Wbe~Y/s-l64.jpg","http://i.ebayimg.com/images/g/63QAAOSwfZ1Wbe~~/s-l64.jpg"],"local":["2015/12/26/gpmt/i_0.jpg","2015/12/26/gpmt/i_1.jpg"]}},{"id":"5lw0","title":"Vintage C1950 4\" Tall Tin Can, Freshly Sunflower Seeds W/original Key Still Full","link":"http://rover.ebay.com/rover/1/711-53200-19255-0/1?campid=5336393622&toolid=10013&customId=advertising/tins&mpre=http://www.ebay.com/itm/361453054697","meta":{"price":2799,"date":{"formatted":"2015-12-26T08:00:00.000Z","origin":"-21 hours ago"},"bids":2,"watchers":1},"src":{"original":"http://thumbs2.ebaystatic.com/m/m13Trvs8i5SIS5Qy3dPyUrw/140.jpg","local":"2015/12/26/5lw0/t.jpg"},"images":{"original":["http://i.ebayimg.com/images/g/TbQAAOSwSHZWdvju/s-l64.jpg","http://i.ebayimg.com/images/g/0KgAAOSwhkRWdvj2/s-l64.jpg"],"local":["2015/12/26/5lw0/i_0.jpg","2015/12/26/5lw0/i_1.jpg"]}},{"id":"k64j","title":"Vintage Bensons English Toffee England Queen Mary Ship Lidded Tin","link":"http://rover.ebay.com/rover/1/711-53200-19255-0/1?campid=5336393622&toolid=10013&customId=advertising/tins&mpre=http://www.ebay.com/itm/361452227312","meta":{"price":2500,"date":{"formatted":"2015-12-26T08:00:00.000Z","origin":"-11 hours ago"},"bids":9,"watchers":3},"src":{"original":"http://thumbs1.ebaystatic.com/m/mmOg8jR4UfQvRtH7mQrOufg/140.jpg","local":"2015/12/26/k64j/t.jpg"},"images":{"original":["http://i.ebayimg.com/images/g/NlQAAOSwSdZWdOW-/s-l64.jpg","http://i.ebayimg.com/images/g/3d8AAOSwhkRWdOXC/s-l64.jpg","http://i.ebayimg.com/images/g/zloAAOSw1S9WdOXG/s-l64.jpg","http://i.ebayimg.com/images/g/d7EAAOSwCQNWdOXL/s-l64.jpg","http://i.ebayimg.com/images/g/NMwAAOSwo3pWdOXR/s-l64.jpg"],"local":["2015/12/26/k64j/i_0.jpg","2015/12/26/k64j/i_1.jpg","2015/12/26/k64j/i_2.jpg","2015/12/26/k64j/i_3.jpg","2015/12/26/k64j/i_4.jpg"]}},{"id":"0nlf","title":"Scarce Vintage Twinings Russian Caravan Tea Tin-4 Oz-third Full (advertising)","link":"http://rover.ebay.com/rover/1/711-53200-19255-0/1?campid=5336393622&toolid=10013&customId=advertising/tins&mpre=http://www.ebay.com/itm/131679914862","meta":{"price":2050,"date":{"formatted":"2015-12-26T08:00:00.000Z","origin":"-16 hours ago"},"bids":8,"watchers":4},"src":{"original":"http://thumbs3.ebaystatic.com/m/mfiUmzuVxphptoOvc4fGkTA/140.jpg","local":"2015/12/26/0nlf/t.jpg"},"images":{"original":["http://i.ebayimg.com/images/g/ePAAAOSwJcZWdJkB/s-l64.jpg","http://i.ebayimg.com/images/g/l88AAOSw1S9WdJjf/s-l64.jpg"],"local":["2015/12/26/0nlf/i_0.jpg","2015/12/26/0nlf/i_1.jpg"]}},{"id":"j929","title":"Vintage Edgeworth Junior Vertical Extra High Grade Tobacco Tin ","link":"http://rover.ebay.com/rover/1/711-53200-19255-0/1?campid=5336393622&toolid=10013&customId=advertising/tins&mpre=http://www.ebay.com/itm/281889503845","meta":{"price":1995,"date":{"formatted":"2015-12-26T08:00:00.000Z","origin":"-11 hours ago"},"bids":8,"watchers":4},"src":{"original":"http://thumbs2.ebaystatic.com/m/m85jng6c3yIfr13Uo0NfpQg/140.jpg","local":"2015/12/26/j929/t.jpg"},"images":{"original":["http://i.ebayimg.com/images/g/cnEAAOSwNyFWdOI8/s-l64.jpg","http://i.ebayimg.com/images/g/r24AAOSwSHZWdOI~/s-l64.jpg","http://i.ebayimg.com/images/g/M1QAAOSw3KFWdOJB/s-l64.jpg"],"local":["2015/12/26/j929/i_0.jpg","2015/12/26/j929/i_1.jpg","2015/12/26/j929/i_2.jpg"]}},{"id":"2xsr","title":"Vintage, Red Wolf Coffee, Steel Cut, 1lb, Tin, No Lid, Kcmo, Kansas City","link":"http://rover.ebay.com/rover/1/711-53200-19255-0/1?campid=5336393622&toolid=10013&customId=advertising/tins&mpre=http://www.ebay.com/itm/331737280177","meta":{"price":1949,"date":{"formatted":"2015-12-26T08:00:00.000Z","origin":"-18 hours ago"},"bids":2,"watchers":1},"src":{"original":"http://thumbs2.ebaystatic.com/m/mQwp-nK6ibwWayvgv7f6_Ng/140.jpg","local":"2015/12/26/2xsr/t.jpg"},"images":{"original":["http://i.ebayimg.com/images/g/w9QAAOSw3KFWcIh-/s-l64.jpg","http://i.ebayimg.com/images/g/FlcAAOSwo3pWcIiW/s-l64.jpg","http://i.ebayimg.com/images/g/K2IAAOSwCQNWcIir/s-l64.jpg","http://i.ebayimg.com/images/g/s9wAAOSwNyFWcIi-/s-l64.jpg","http://i.ebayimg.com/images/g/O4IAAOSwk1JWcIjY/s-l64.jpg","http://i.ebayimg.com/images/g/t08AAOSwNyFWcIjo/s-l64.jpg"],"local":["2015/12/26/2xsr/i_0.jpg","2015/12/26/2xsr/i_1.jpg","2015/12/26/2xsr/i_2.jpg","2015/12/26/2xsr/i_3.jpg","2015/12/26/2xsr/i_4.jpg","2015/12/26/2xsr/i_5.jpg"]}},{"id":"0wz5","title":"Friends Tobacco Tin With Lid And Opener Lorillard Co Louisville Ky","link":"http://rover.ebay.com/rover/1/711-53200-19255-0/1?campid=5336393622&toolid=10013&customId=advertising/tins&mpre=http://www.ebay.com/itm/252215250377","meta":{"price":1699,"date":{"formatted":"2015-12-26T08:00:00.000Z","origin":"-56 mins ago"},"bids":1,"watchers":0},"src":{"original":"http://thumbs2.ebaystatic.com/m/mC6W-2U64YjI1pY0z-VcHig/140.jpg","local":"2015/12/26/0wz5/t.jpg"},"images":{"original":["http://i.ebayimg.com/images/g/Ft4AAOSwNphWZ6Y1/s-l64.jpg","http://i.ebayimg.com/images/g/FxMAAOSwNphWZ6Y5/s-l64.jpg","http://i.ebayimg.com/images/g/CwAAAOSwf-VWZ6Y-/s-l64.jpg","http://i.ebayimg.com/images/g/xb4AAOSwfZ1WZ6ZD/s-l64.jpg","http://i.ebayimg.com/images/g/mQEAAOSwAKxWZ6ZI/s-l64.jpg","http://i.ebayimg.com/images/g/HK0AAOSwbdpWZ6ZN/s-l64.jpg","http://i.ebayimg.com/images/g/HRIAAOSwbdpWZ6ZS/s-l64.jpg","http://i.ebayimg.com/images/g/GUgAAOSwNphWZ6ZX/s-l64.jpg","http://i.ebayimg.com/images/g/GagAAOSwNphWZ6Zc/s-l64.jpg"],"local":["2015/12/26/0wz5/i_0.jpg","2015/12/26/0wz5/i_1.jpg","2015/12/26/0wz5/i_2.jpg","2015/12/26/0wz5/i_3.jpg","2015/12/26/0wz5/i_4.jpg","2015/12/26/0wz5/i_5.jpg","2015/12/26/0wz5/i_6.jpg","2015/12/26/0wz5/i_7.jpg","2015/12/26/0wz5/i_8.jpg"]}},{"id":"lozq","title":"Roundys Pineapple Can Country Store Tin Milwaukee Wisconsin","link":"http://rover.ebay.com/rover/1/711-53200-19255-0/1?campid=5336393622&toolid=10013&customId=advertising/tins&mpre=http://www.ebay.com/itm/281889401692","meta":{"price":1650,"date":{"formatted":"2015-12-26T08:00:00.000Z","origin":"-15 hours ago"},"bids":3,"watchers":3},"src":{"original":"http://thumbs1.ebaystatic.com/m/mlPLnvJvpjckB6oAYc5h2Ig/140.jpg","local":"2015/12/26/lozq/t.jpg"},"images":{"original":["http://i.ebayimg.com/images/g/ZVQAAOSwv-NWZikR/s-l64.jpg","http://i.ebayimg.com/images/g/ZhQAAOSwv-NWZikc/s-l64.jpg","http://i.ebayimg.com/images/g/idQAAOSwwE5WZikl/s-l64.jpg","http://i.ebayimg.com/images/g/w28AAOSwcBhWZiku/s-l64.jpg","http://i.ebayimg.com/images/g/RnMAAOSw7FRWZik5/s-l64.jpg","http://i.ebayimg.com/images/g/BUIAAOSwf-VWZilD/s-l64.jpg"],"local":["2015/12/26/lozq/i_0.jpg","2015/12/26/lozq/i_1.jpg","2015/12/26/lozq/i_2.jpg","2015/12/26/lozq/i_3.jpg","2015/12/26/lozq/i_4.jpg","2015/12/26/lozq/i_5.jpg"]}},{"id":"do51","title":"British Sphinx Log Cabin Flaked Gold Leaf Cavendish Lambert&butler's Tobacco Tin","link":"http://rover.ebay.com/rover/1/711-53200-19255-0/1?campid=5336393622&toolid=10013&customId=advertising/tins&mpre=http://www.ebay.com/itm/381493506262","meta":{"price":1500,"date":{"formatted":"2015-12-26T08:00:00.000Z","origin":"-8 hours ago"},"bids":1,"watchers":2},"src":{"original":"http://thumbs3.ebaystatic.com/m/m6ptBio7jwE8zUtlMixv3GA/140.jpg","local":"2015/12/26/do51/t.jpg"},"images":{"original":["http://i.ebayimg.com/images/g/gbAAAOSwo3pWcR3j/s-l64.jpg","http://i.ebayimg.com/images/g/iRsAAOSwCQNWcR3e/s-l64.jpg"],"local":["2015/12/26/do51/i_0.jpg","2015/12/26/do51/i_1.jpg"]}},{"id":"l4s5","title":"Vintage Nabisco Premium Saltine Crackers Tin 1969 Collectible Display","link":"http://rover.ebay.com/rover/1/711-53200-19255-0/1?campid=5336393622&toolid=10013&customId=advertising/tins&mpre=http://www.ebay.com/itm/191760676334","meta":{"price":1499,"date":{"formatted":"2015-12-26T08:00:00.000Z","origin":"-21 hours ago"},"bids":1,"watchers":0},"src":{"original":"http://thumbs3.ebaystatic.com/m/m8HAp8gMyulzxzmH4kfftBw/140.jpg","local":"2015/12/26/l4s5/t.jpg"},"images":{"original":["http://i.ebayimg.com/images/g/dAEAAOSwZ1lWcFvq/s-l64.jpg","http://i.ebayimg.com/images/g/vssAAOSwNyFWcFvQ/s-l64.jpg","http://i.ebayimg.com/images/g/iHcAAOSwCQNWcFu7/s-l64.jpg","http://i.ebayimg.com/images/g/a~EAAOSwZ1lWcFua/s-l64.jpg","http://i.ebayimg.com/images/g/tMMAAOSwUdlWcFtP/s-l64.jpg","http://i.ebayimg.com/images/g/ygoAAOSw1S9WcFtT/s-l64.jpg","http://i.ebayimg.com/images/g/U1IAAOSwYaFWcFtY/s-l64.jpg","http://i.ebayimg.com/images/g/y2oAAOSw1S9WcFte/s-l64.jpg"],"local":["2015/12/26/l4s5/i_0.jpg","2015/12/26/l4s5/i_1.jpg","2015/12/26/l4s5/i_2.jpg","2015/12/26/l4s5/i_3.jpg","2015/12/26/l4s5/i_4.jpg","2015/12/26/l4s5/i_5.jpg","2015/12/26/l4s5/i_6.jpg","2015/12/26/l4s5/i_7.jpg"]}},{"id":"625q","title":"Vintage Holiday Pipe Mixture Tobacco Tin Christmas Santa Claus & Tree Label","link":"http://rover.ebay.com/rover/1/711-53200-19255-0/1?campid=5336393622&toolid=10013&customId=advertising/tins&mpre=http://www.ebay.com/itm/111853381612","meta":{"price":1299,"date":{"formatted":"2015-12-26T08:00:00.000Z","origin":"-17 hours ago"},"bids":1,"watchers":6},"src":{"original":"http://thumbs1.ebaystatic.com/m/mnBoGZvIcjp2FPZrAKByIJQ/140.jpg","local":"2015/12/26/625q/t.jpg"},"images":{"original":["http://i.ebayimg.com/images/g/FMIAAOSwnH1WYdis/s-l300.jpg"],"local":["2015/12/26/625q/i_0.jpg"]}},{"id":"ks50","title":"Scarce Vintage Twinings Lapsang Souchong Tea Tin-4 Oz-part Full (advertising)","link":"http://rover.ebay.com/rover/1/711-53200-19255-0/1?campid=5336393622&toolid=10013&customId=advertising/tins&mpre=http://www.ebay.com/itm/131679931115","meta":{"price":1050,"date":{"formatted":"2015-12-26T08:00:00.000Z","origin":"-16 hours ago"},"bids":2,"watchers":6},"src":{"original":"http://thumbs4.ebaystatic.com/m/mB9HuRXDpL3rkzBR7rijC1g/140.jpg","local":"2015/12/26/ks50/t.jpg"},"images":{"original":["http://i.ebayimg.com/images/g/0GUAAOSwNyFWdKFS/s-l300.jpg"],"local":["2015/12/26/ks50/i_0.jpg"]}},{"id":"pe48","title":"Antique Advertising Spice Tin Container A&p Sultana Spice Mills Mustard","link":"http://rover.ebay.com/rover/1/711-53200-19255-0/1?campid=5336393622&toolid=10013&customId=advertising/tins&mpre=http://www.ebay.com/itm/191762642361","meta":{"price":1000,"date":{"formatted":"2015-12-26T08:00:00.000Z","origin":"-17 hours ago"},"bids":1,"watchers":8},"src":{"original":"http://thumbs2.ebaystatic.com/m/m3CkgW_1BR0E7fDR63hU2Yg/140.jpg","local":"2015/12/26/pe48/t.jpg"},"images":{"original":["http://i.ebayimg.com/images/g/unMAAOSwnipWa1C-/s-l64.jpg","http://i.ebayimg.com/images/g/opoAAOSwNphWa1DD/s-l64.jpg","http://i.ebayimg.com/images/g/oF4AAOSwfZ1Wa1DI/s-l64.jpg","http://i.ebayimg.com/images/g/qbgAAOSw8-tWa1DP/s-l64.jpg","http://i.ebayimg.com/images/g/yQAAAOSwcOFWa1DV/s-l64.jpg"],"local":["2015/12/26/pe48/i_0.jpg","2015/12/26/pe48/i_1.jpg","2015/12/26/pe48/i_2.jpg","2015/12/26/pe48/i_3.jpg","2015/12/26/pe48/i_4.jpg"]}},{"id":"hyty","title":"Vintage Lunch Pail Tin Union Leader Cut Plug","link":"http://rover.ebay.com/rover/1/711-53200-19255-0/1?campid=5336393622&toolid=10013&customId=advertising/tins&mpre=http://www.ebay.com/itm/262198849045","meta":{"price":999,"date":{"formatted":"2015-12-26T08:00:00.000Z","origin":"-16 hours ago"},"bids":1,"watchers":1},"src":{"original":"http://thumbs2.ebaystatic.com/m/mfZahB4kHOeonq84A-XkY0w/140.jpg","local":"2015/12/26/hyty/t.jpg"},"images":{"original":["http://i.ebayimg.com/images/g/vHYAAOSw5IJWdHGA/s-l64.jpg","http://i.ebayimg.com/images/g/ckcAAOSw1S9WdHF~/s-l64.jpg","http://i.ebayimg.com/images/g/dbwAAOSwHPlWdHGA/s-l64.jpg","http://i.ebayimg.com/images/g/tF0AAOSw~otWdHF~/s-l64.jpg","http://i.ebayimg.com/images/g/Yj0AAOSw3KFWdHF~/s-l64.jpg"],"local":["2015/12/26/hyty/i_0.jpg","2015/12/26/hyty/i_1.jpg","2015/12/26/hyty/i_2.jpg","2015/12/26/hyty/i_3.jpg","2015/12/26/hyty/i_4.jpg"]}},{"id":"rqzs","title":"Union Leader Cut Plug Tobacco Tin Early (1900's)","link":"http://rover.ebay.com/rover/1/711-53200-19255-0/1?campid=5336393622&toolid=10013&customId=advertising/tins&mpre=http://www.ebay.com/itm/291642969151","meta":{"price":999,"date":{"formatted":"2015-12-26T08:00:00.000Z","origin":"-18 hours ago"},"bids":1,"watchers":1},"src":{"original":"http://thumbs4.ebaystatic.com/m/m1LdsLCXZSmLN-AmNmvmtIg/140.jpg","local":"2015/12/26/rqzs/t.jpg"},"images":{"original":["http://i.ebayimg.com/images/g/KJwAAOSwZ1lWdlrb/s-l64.jpg","http://i.ebayimg.com/images/g/r6UAAOSwYaFWdlrk/s-l64.jpg","http://i.ebayimg.com/images/g/SRIAAOSw3KFWdlrn/s-l64.jpg","http://i.ebayimg.com/images/g/7h0AAOSwo3pWdlrv/s-l64.jpg","http://i.ebayimg.com/images/g/w0MAAOSwJcZWdlr4/s-l64.jpg","http://i.ebayimg.com/images/g/SjoAAOSw3KFWdlsB/s-l64.jpg"],"local":["2015/12/26/rqzs/i_0.jpg","2015/12/26/rqzs/i_1.jpg","2015/12/26/rqzs/i_2.jpg","2015/12/26/rqzs/i_3.jpg","2015/12/26/rqzs/i_4.jpg","2015/12/26/rqzs/i_5.jpg"]}},{"id":"zhg0","title":"Vintage Shedd's Peanut Butter Advertising Tin Pail Bucket Red Cover. ","link":"http://rover.ebay.com/rover/1/711-53200-19255-0/1?campid=5336393622&toolid=10013&customId=advertising/tins&mpre=http://www.ebay.com/itm/121845246160","meta":{"price":849,"date":{"formatted":"2015-12-26T08:00:00.000Z","origin":"-14 hours ago"},"bids":3,"watchers":2},"src":{"original":"http://thumbs1.ebaystatic.com/m/mL5mgghHYtMI0AictGhostA/140.jpg","local":"2015/12/26/zhg0/t.jpg"},"images":{"original":["http://i.ebayimg.com/images/g/BXoAAOSw5IJWd188/s-l64.jpg","http://i.ebayimg.com/images/g/4ekAAOSwSdZWd188/s-l64.jpg","http://i.ebayimg.com/images/g/WscAAOSwNyFWd186/s-l64.jpg","http://i.ebayimg.com/images/g/mpUAAOSwUdlWd186/s-l64.jpg","http://i.ebayimg.com/images/g/d1QAAOSwo3pWd186/s-l64.jpg","http://i.ebayimg.com/images/g/d1YAAOSwo3pWd186/s-l64.jpg","http://i.ebayimg.com/images/g/juAAAOSw1S9Wd186/s-l64.jpg","http://i.ebayimg.com/images/g/4c0AAOSwSdZWd186/s-l64.jpg","http://i.ebayimg.com/images/g/bEsAAOSwJcZWd188/s-l64.jpg","http://i.ebayimg.com/images/g/ELIAAOSwYaFWd188/s-l64.jpg","http://i.ebayimg.com/images/g/jvoAAOSw1S9Wd188/s-l64.jpg"],"local":["2015/12/26/zhg0/i_0.jpg","2015/12/26/zhg0/i_1.jpg","2015/12/26/zhg0/i_2.jpg","2015/12/26/zhg0/i_3.jpg","2015/12/26/zhg0/i_4.jpg","2015/12/26/zhg0/i_5.jpg","2015/12/26/zhg0/i_6.jpg","2015/12/26/zhg0/i_7.jpg","2015/12/26/zhg0/i_8.jpg","2015/12/26/zhg0/i_9.jpg","2015/12/26/zhg0/i_10.jpg"]}},{"id":"lojp","title":"Vintage Kitty Cat Octagon Tin Box Sewing Bin Container Yarn Hinged Lid","link":"http://rover.ebay.com/rover/1/711-53200-19255-0/1?campid=5336393622&toolid=10013&customId=advertising/tins&mpre=http://www.ebay.com/itm/331736444242","meta":{"price":825,"date":{"formatted":"2015-12-26T08:00:00.000Z","origin":"-3 hours ago"},"bids":1,"watchers":1},"src":{"original":"http://thumbs3.ebaystatic.com/m/mJ8WDzwJ6hRHpRsCc032PTg/140.jpg","local":"2015/12/26/lojp/t.jpg"},"images":{"original":["http://i.ebayimg.com/images/g/S-cAAOSwHnFVtRwN/s-l64.jpg","http://i.ebayimg.com/images/g/0sIAAOSwyQtVtRv~/s-l64.jpg","http://i.ebayimg.com/images/g/xj8AAOSw3ydVtRwc/s-l64.jpg","http://i.ebayimg.com/images/g/KygAAOSwMmBVtRwp/s-l64.jpg","http://i.ebayimg.com/images/g/ApcAAOSw9N1VtRw2/s-l64.jpg","http://i.ebayimg.com/images/g/b2QAAOSwjVVVtRxJ/s-l64.jpg","http://i.ebayimg.com/images/g/ZPUAAOSwgQ9VtRxW/s-l64.jpg","http://i.ebayimg.com/images/g/6s8AAOSwDNdVtRxz/s-l64.jpg","http://i.ebayimg.com/images/g/zB0AAOSwPcVVtRyE/s-l64.jpg","http://i.ebayimg.com/images/g/UfYAAOSwLVZVtRyb/s-l64.jpg"],"local":["2015/12/26/lojp/i_0.jpg","2015/12/26/lojp/i_1.jpg","2015/12/26/lojp/i_2.jpg","2015/12/26/lojp/i_3.jpg","2015/12/26/lojp/i_4.jpg","2015/12/26/lojp/i_5.jpg","2015/12/26/lojp/i_6.jpg","2015/12/26/lojp/i_7.jpg","2015/12/26/lojp/i_8.jpg","2015/12/26/lojp/i_9.jpg"]}},{"id":"74od","title":"Vintage Container Lot (1) Cardinal Lighter Fluid & (1) Challange Cycle Oil ","link":"http://rover.ebay.com/rover/1/711-53200-19255-0/1?campid=5336393622&toolid=10013&customId=advertising/tins&mpre=http://www.ebay.com/itm/191762724278","meta":{"price":800,"date":{"formatted":"2015-12-26T08:00:00.000Z","origin":"-15 hours ago"},"bids":1,"watchers":1},"src":{"original":"http://thumbs3.ebaystatic.com/m/mpEWUjJXo176g_raTvCTjpw/140.jpg","local":"2015/12/26/74od/t.jpg"},"images":{"original":["http://i.ebayimg.com/images/g/4SEAAOSwp5JWawUd/s-l64.jpg","http://i.ebayimg.com/images/g/6~EAAOSwcBhWawUs/s-l64.jpg","http://i.ebayimg.com/images/g/aUkAAOSwbdpWawU4/s-l64.jpg","http://i.ebayimg.com/images/g/uPEAAOSwcOFWawVC/s-l64.jpg","http://i.ebayimg.com/images/g/WvEAAOSw8-tWawVN/s-l64.jpg"],"local":["2015/12/26/74od/i_0.jpg","2015/12/26/74od/i_1.jpg","2015/12/26/74od/i_2.jpg","2015/12/26/74od/i_3.jpg","2015/12/26/74od/i_4.jpg"]}},{"id":"m9z5","title":"Vintage White House Coffee Tin Paper Label Dwinell - Wright Boston-chicago","link":"http://rover.ebay.com/rover/1/711-53200-19255-0/1?campid=5336393622&toolid=10013&customId=advertising/tins&mpre=http://www.ebay.com/itm/181966496508","meta":{"price":750,"date":{"formatted":"2015-12-26T08:00:00.000Z","origin":"-14 hours ago"},"bids":1,"watchers":2},"src":{"original":"http://thumbs1.ebaystatic.com/m/m00H-I0E58-4IjRifv4d13A/140.jpg","local":"2015/12/26/m9z5/t.jpg"},"images":{"original":["http://i.ebayimg.com/images/g/Ml0AAOSwfZ1Wa2Fr/s-l64.jpg","http://i.ebayimg.com/images/g/MsAAAOSwfZ1Wa2Fv/s-l64.jpg","http://i.ebayimg.com/images/g/3bYAAOSwv-NWa2Fy/s-l64.jpg","http://i.ebayimg.com/images/g/3gwAAOSwv-NWa2F1/s-l64.jpg","http://i.ebayimg.com/images/g/ioMAAOSwnH1Wa2F7/s-l64.jpg","http://i.ebayimg.com/images/g/5xEAAOSwAKxWa2GD/s-l64.jpg","http://i.ebayimg.com/images/g/i6oAAOSwnH1Wa2GI/s-l64.jpg","http://i.ebayimg.com/images/g/eWwAAOSwbdpWa2Fn/s-l64.jpg","http://i.ebayimg.com/images/g/mYYAAOSwfZ1Wa2Wp/s-l64.jpg"],"local":["2015/12/26/m9z5/i_0.jpg","2015/12/26/m9z5/i_1.jpg","2015/12/26/m9z5/i_2.jpg","2015/12/26/m9z5/i_3.jpg","2015/12/26/m9z5/i_4.jpg","2015/12/26/m9z5/i_5.jpg","2015/12/26/m9z5/i_6.jpg","2015/12/26/m9z5/i_7.jpg","2015/12/26/m9z5/i_8.jpg"]}},{"id":"m81p","title":"Vintage Rawleigh's Cream Of Tartar Antique Spice Tin Blue/pink Freeport Illinois","link":"http://rover.ebay.com/rover/1/711-53200-19255-0/1?campid=5336393622&toolid=10013&customId=advertising/tins&mpre=http://www.ebay.com/itm/252218099250","meta":{"price":750,"date":{"formatted":"2015-12-26T08:00:00.000Z","origin":"-17 hours ago"},"bids":1,"watchers":2},"src":{"original":"http://thumbs3.ebaystatic.com/m/mNjBY43YGOXs1TTpEn-0QTQ/140.jpg","local":"2015/12/26/m81p/t.jpg"},"images":{"original":["http://i.ebayimg.com/images/g/GsYAAOSwHQ9Wa1dK/s-l64.jpg","http://i.ebayimg.com/images/g/G~AAAOSwHQ9Wa1da/s-l64.jpg","http://i.ebayimg.com/images/g/SDgAAOSwfZ1Wa1de/s-l64.jpg","http://i.ebayimg.com/images/g/uO4AAOSwbdpWa1dj/s-l64.jpg","http://i.ebayimg.com/images/g/uUwAAOSwbdpWa1do/s-l64.jpg","http://i.ebayimg.com/images/g/tpEAAOSwnH1Wa1ds/s-l64.jpg","http://i.ebayimg.com/images/g/ujAAAOSwbdpWa1dy/s-l64.jpg","http://i.ebayimg.com/images/g/QbYAAOSwNphWa1d3/s-l64.jpg","http://i.ebayimg.com/images/g/P10AAOSw8-tWa1d7/s-l64.jpg","http://i.ebayimg.com/images/g/uzAAAOSwbdpWa1d~/s-l64.jpg"],"local":["2015/12/26/m81p/i_0.jpg","2015/12/26/m81p/i_1.jpg","2015/12/26/m81p/i_2.jpg","2015/12/26/m81p/i_3.jpg","2015/12/26/m81p/i_4.jpg","2015/12/26/m81p/i_5.jpg","2015/12/26/m81p/i_6.jpg","2015/12/26/m81p/i_7.jpg","2015/12/26/m81p/i_8.jpg","2015/12/26/m81p/i_9.jpg"]}},{"id":"qkcp","title":"Crawfords Biscuits Sample Biscuit Tin Tortoiseshell Mother Of Pearl","link":"http://rover.ebay.com/rover/1/711-53200-19255-0/1?campid=5336393622&toolid=10013&customId=advertising/tins&mpre=http://www.ebay.com/itm/221970296817","meta":{"price":746,"date":{"formatted":"2015-12-26T08:00:00.000Z","origin":"-6 hours ago"},"bids":1,"watchers":2},"src":{"original":"http://thumbs2.ebaystatic.com/m/mUHoVp0f0hfwr4Hj79Kj48w/140.jpg","local":"2015/12/26/qkcp/t.jpg"},"images":{"original":["http://i.ebayimg.com/images/g/wjcAAOSw3KFWcTaN/s-l64.jpg","http://i.ebayimg.com/images/g/gs0AAOSwSHZWcTab/s-l64.jpg","http://i.ebayimg.com/images/g/o18AAOSwCQNWcTag/s-l64.jpg"],"local":["2015/12/26/qkcp/i_0.jpg","2015/12/26/qkcp/i_1.jpg","2015/12/26/qkcp/i_2.jpg"]}},{"id":"9al9","title":"Vintage Edgeworth Tobacco Tin ","link":"http://rover.ebay.com/rover/1/711-53200-19255-0/1?campid=5336393622&toolid=10013&customId=advertising/tins&mpre=http://www.ebay.com/itm/281889208898","meta":{"price":627,"date":{"formatted":"2015-12-26T08:00:00.000Z","origin":"-21 hours ago"},"bids":2,"watchers":2},"src":{"original":"http://thumbs3.ebaystatic.com/m/mzGQeNC2OvQSPD1of33kVJQ/140.jpg","local":"2015/12/26/9al9/t.jpg"},"images":{"original":["http://i.ebayimg.com/images/g/ieIAAOSwEgVWRP32/s-l64.jpg","http://i.ebayimg.com/images/g/uBgAAOSwLzdWRP5O/s-l64.jpg","http://i.ebayimg.com/images/g/ubUAAOSwLzdWRP5c/s-l64.jpg","http://i.ebayimg.com/images/g/i6MAAOSw4UtWRP5p/s-l64.jpg","http://i.ebayimg.com/images/g/HtcAAOSwIwhWRP55/s-l64.jpg","http://i.ebayimg.com/images/g/sv4AAOSwsFpWRP6G/s-l64.jpg","http://i.ebayimg.com/images/g/HHkAAOSweuxWRP6V/s-l64.jpg"],"local":["2015/12/26/9al9/i_0.jpg","2015/12/26/9al9/i_1.jpg","2015/12/26/9al9/i_2.jpg","2015/12/26/9al9/i_3.jpg","2015/12/26/9al9/i_4.jpg","2015/12/26/9al9/i_5.jpg","2015/12/26/9al9/i_6.jpg"]}},{"id":"6ow7","title":"Vintage Tin Box Tobacco Cigarette/medina Tyrkisk Cigaretu00bb","link":"http://rover.ebay.com/rover/1/711-53200-19255-0/1?campid=5336393622&toolid=10013&customId=advertising/tins&mpre=http://www.ebay.com/itm/262199095901","meta":{"price":400,"date":{"formatted":"2015-12-26T08:00:00.000Z","origin":"-10 hours ago"},"bids":1,"watchers":0},"src":{"original":"http://thumbs2.ebaystatic.com/m/mQh3oddOykqyn15jswT6dzw/140.jpg","local":"2015/12/26/6ow7/t.jpg"},"images":{"original":["http://i.ebayimg.com/images/g/0DAAAOSwp5JWT85J/s-l64.jpg","http://i.ebayimg.com/images/g/wSwAAOSwcBhWT85n/s-l64.jpg","http://i.ebayimg.com/images/g/D0AAAOSwnipWT85-/s-l64.jpg","http://i.ebayimg.com/images/g/TpYAAOSwgyxWT86Y/s-l64.jpg","http://i.ebayimg.com/images/g/4-8AAOSwxN5WT86q/s-l64.jpg","http://i.ebayimg.com/images/g/UNcAAOSwgyxWT86~/s-l64.jpg"],"local":["2015/12/26/6ow7/i_0.jpg","2015/12/26/6ow7/i_1.jpg","2015/12/26/6ow7/i_2.jpg","2015/12/26/6ow7/i_3.jpg","2015/12/26/6ow7/i_4.jpg","2015/12/26/6ow7/i_5.jpg"]}},{"id":"hnex","title":"Rare Tobacco Tin Rare Smoking Pipe Pouch Macbaren Virginia No 1 Special Blend","link":"http://rover.ebay.com/rover/1/711-53200-19255-0/1?campid=5336393622&toolid=10013&customId=advertising/tins&mpre=http://www.ebay.com/itm/272081572873","meta":{"price":363,"date":{"formatted":"2015-12-26T08:00:00.000Z","origin":"-16 hours ago"},"bids":1,"watchers":2},"src":{"original":"http://thumbs2.ebaystatic.com/m/m-Z_BdLslSsaG0Rb-_IU1tg/140.jpg","local":"2015/12/26/hnex/t.jpg"},"images":{"original":["http://i.ebayimg.com/images/g/LAQAAOSwNphWa2Ir/s-l300.jpg"],"local":["2015/12/26/hnex/i_0.jpg"]}},{"id":"oigm","title":"Vintage Original John Cope's Fancy Dried Sweet Corn Tin & Contents Manheim, Pa","link":"http://rover.ebay.com/rover/1/711-53200-19255-0/1?campid=5336393622&toolid=10013&customId=advertising/tins&mpre=http://www.ebay.com/itm/331736064867","meta":{"price":225,"date":{"formatted":"2015-12-26T08:00:00.000Z","origin":"-20 hours ago"},"bids":1,"watchers":0},"src":{"original":"http://thumbs4.ebaystatic.com/m/mdRLSwMRfMdpW1S5VMiNbiA/140.jpg","local":"2015/12/26/oigm/t.jpg"},"images":{"original":["http://i.ebayimg.com/images/g/lloAAOSwZjJU81pY/s-l64.jpg","http://i.ebayimg.com/images/g/9ZsAAOSwBahU81pd/s-l64.jpg","http://i.ebayimg.com/images/g/d8YAAOSwstxU81pj/s-l64.jpg","http://i.ebayimg.com/images/g/YGEAAOSwe-FU81pp/s-l64.jpg","http://i.ebayimg.com/images/g/7MgAAOSwBLlU81pu/s-l64.jpg","http://i.ebayimg.com/images/g/YrYAAOSwv0tU81p0/s-l64.jpg","http://i.ebayimg.com/images/g/Y7IAAOSwv0tU81p7/s-l64.jpg"],"local":["2015/12/26/oigm/i_0.jpg","2015/12/26/oigm/i_1.jpg","2015/12/26/oigm/i_2.jpg","2015/12/26/oigm/i_3.jpg","2015/12/26/oigm/i_4.jpg","2015/12/26/oigm/i_5.jpg","2015/12/26/oigm/i_6.jpg"]}},{"id":"k31j","title":"F. W. Mcness Pure Ground Allspice 3 Oz Tin Container","link":"http://rover.ebay.com/rover/1/711-53200-19255-0/1?campid=5336393622&toolid=10013&customId=advertising/tins&mpre=http://www.ebay.com/itm/331736138523","meta":{"price":220,"date":{"formatted":"2015-12-26T08:00:00.000Z","origin":"-18 hours ago"},"bids":2,"watchers":1},"src":{"original":"http://thumbs4.ebaystatic.com/m/mByKGJDq2wQDUWQjl-QwkUQ/140.jpg","local":"2015/12/26/k31j/t.jpg"},"images":{"original":["http://i.ebayimg.com/images/g/8SMAAOSw7aBVEycQ/s-l64.jpg","http://i.ebayimg.com/images/g/kFwAAOSwPhdVEycY/s-l64.jpg","http://i.ebayimg.com/images/g/3pgAAOSwv0tVEycg/s-l64.jpg","http://i.ebayimg.com/images/g/7k8AAOSwEeFVEycn/s-l64.jpg","http://i.ebayimg.com/images/g/t5EAAOSwBahVEycw/s-l64.jpg","http://i.ebayimg.com/images/g/AwkAAOSwrklVEyc4/s-l64.jpg"],"local":["2015/12/26/k31j/i_0.jpg","2015/12/26/k31j/i_1.jpg","2015/12/26/k31j/i_2.jpg","2015/12/26/k31j/i_3.jpg","2015/12/26/k31j/i_4.jpg","2015/12/26/k31j/i_5.jpg"]}},{"id":"gvxz","title":"Vintage Players Sun Valley Tobacco Tin","link":"http://rover.ebay.com/rover/1/711-53200-19255-0/1?campid=5336393622&toolid=10013&customId=advertising/tins&mpre=http://www.ebay.com/itm/141856618067","meta":{"price":199,"date":{"formatted":"2015-12-26T08:00:00.000Z","origin":"-3 hours ago"},"bids":1,"watchers":2},"src":{"original":"http://thumbs4.ebaystatic.com/m/muXgcdzPg-4X1ZCmfVX1fJg/140.jpg","local":"2015/12/26/gvxz/t.jpg"},"images":{"original":["http://i.ebayimg.com/images/g/czwAAOSwNphWXxzu/s-l64.jpg","http://i.ebayimg.com/images/g/xAQAAOSwHQ9WXx0C/s-l64.jpg","http://i.ebayimg.com/images/g/BekAAOSwnipWXx0i/s-l64.jpg"],"local":["2015/12/26/gvxz/i_0.jpg","2015/12/26/gvxz/i_1.jpg","2015/12/26/gvxz/i_2.jpg"]}},{"id":"mqjw","title":"Vintage Hershey's Kiss Tin And Plush Kiss Magnet ","link":"http://rover.ebay.com/rover/1/711-53200-19255-0/1?campid=5336393622&toolid=10013&customId=advertising/tins&mpre=http://www.ebay.com/itm/111855027842","meta":{"price":199,"date":{"formatted":"2015-12-26T08:00:00.000Z","origin":"-10 hours ago"},"bids":2,"watchers":1},"src":{"original":"http://thumbs3.ebaystatic.com/m/moOdueQDZ9zTZXEeAaTG6yw/140.jpg","local":"2015/12/26/mqjw/t.jpg"},"images":{"original":["http://i.ebayimg.com/images/g/k9AAAOSwAKxWaFf4/s-l64.jpg","http://i.ebayimg.com/images/g/gioAAOSwAYtWODBi/s-l64.jpg","http://i.ebayimg.com/images/g/eX0AAOSwNphWaFgJ/s-l64.jpg","http://i.ebayimg.com/images/g/be4AAOSwcBhWaFgb/s-l64.jpg"],"local":["2015/12/26/mqjw/i_0.jpg","2015/12/26/mqjw/i_1.jpg","2015/12/26/mqjw/i_2.jpg","2015/12/26/mqjw/i_3.jpg"]}},{"id":"vck8","title":"Vintage Amphora Mild Cavendish Red Pipe Tobacco Tin 12 Oz Douwe Egberts","link":"http://rover.ebay.com/rover/1/711-53200-19255-0/1?campid=5336393622&toolid=10013&customId=advertising/tins&mpre=http://www.ebay.com/itm/281889096673","meta":{"price":144,"date":{"formatted":"2015-12-26T08:00:00.000Z","origin":"-23 hours ago"},"bids":1,"watchers":0},"src":{"original":"http://thumbs2.ebaystatic.com/m/m9CgLNjrlPBWAyBhWgRxEWw/140.jpg","local":"2015/12/26/vck8/t.jpg"},"images":{"original":["http://i.ebayimg.com/images/g/bF0AAOSw8-tWYNo2/s-l64.jpg","http://i.ebayimg.com/images/g/QM4AAOSwv-NWYNxA/s-l64.jpg","http://i.ebayimg.com/images/g/8ekAAOSwp5JWYNxH/s-l64.jpg","http://i.ebayimg.com/images/g/RZgAAOSwHQ9WYNxQ/s-l64.jpg","http://i.ebayimg.com/images/g/LA8AAOSwnH1WYNwq/s-l64.jpg","http://i.ebayimg.com/images/g/Qn8AAOSwHQ9WYNws/s-l64.jpg"],"local":["2015/12/26/vck8/i_0.jpg","2015/12/26/vck8/i_1.jpg","2015/12/26/vck8/i_2.jpg","2015/12/26/vck8/i_3.jpg","2015/12/26/vck8/i_4.jpg","2015/12/26/vck8/i_5.jpg"]}}]